{
  "generatedAt": 1780510877338,
  "market": "TW",
  "scanAt": "2026-06-03T18:10:44.410Z",
  "session": "AFTERNOON SESSION (last 2 hours before close)",
  "sessionShort": "afternoon",
  "watchLabel": "收盤前關注",
  "macros": {
    "spy": {
      "last": 755.38,
      "changePct": -0.55
    },
    "vix": {
      "last": 16.08,
      "changePct": 1.97
    },
    "tnx": {
      "last": 4.49,
      "changePct": 0.76
    },
    "dxy": {
      "last": 99.54,
      "changePct": 0.32
    }
  },
  "sectorLeaders": [
    {
      "etf": "IBB",
      "last": 167.12,
      "changePct": 1.73
    },
    {
      "etf": "XLE",
      "last": 58.78,
      "changePct": 1.42
    },
    {
      "etf": "SMH",
      "last": 639.13,
      "changePct": 1.09
    }
  ],
  "sectorLaggards": [
    {
      "etf": "IGV",
      "last": 100.4,
      "changePct": -4.13
    },
    {
      "etf": "GDX",
      "last": 85.36,
      "changePct": -3.06
    },
    {
      "etf": "XAR",
      "last": 275.04,
      "changePct": -1.52
    }
  ],
  "gainers": [
    {
      "symbol": "ABVX",
      "name": "Abivax SA",
      "changePct": 24.22
    },
    {
      "symbol": "NVTS",
      "name": "Navitas Semiconductor Corporat",
      "changePct": 23.38
    },
    {
      "symbol": "MMED",
      "name": "MiniMed Group, Inc.",
      "changePct": 17.6
    },
    {
      "symbol": "TGTX",
      "name": "TG Therapeutics, Inc.",
      "changePct": 11.38
    },
    {
      "symbol": "STRL",
      "name": "Sterling Infrastructure, Inc.",
      "changePct": 10.51
    }
  ],
  "losers": [
    {
      "symbol": "LUNR",
      "name": "Intuitive Machines, Inc.",
      "changePct": -15.11
    },
    {
      "symbol": "MLYS",
      "name": "Mineralys Therapeutics, Inc.",
      "changePct": -13.38
    },
    {
      "symbol": "XNDU",
      "name": "Xanadu Quantum Technologies Li",
      "changePct": -12.64
    },
    {
      "symbol": "ONDS",
      "name": "Ondas Inc",
      "changePct": -12.24
    },
    {
      "symbol": "COMP",
      "name": "Compass, Inc.",
      "changePct": -11.65
    }
  ],
  "narrative": "今日市場呈現選擇性風險偏好，SPY小幅回檔-0.55%但VIX溫和上升至16.08，反映波動率溫和擴大。IBB生科領漲1.73%、XLE能源漲1.42%，而IGV軟體重挫-4.13%、GDX黃金礦業跌-3.06%，顯示資金從防禦性資產與高成長科技轉向生醫與能源。台股強勢，2337.TW、2360.TW、3037.TW等四大獲利族群持續領漲，RS值95-99反映強勢動能。10Y收益率升至4.49%推升風險資產壓力。午盤料溫和整理後試圖收復失地，惟軟體股拋售壓力待觀察。",
  "headline": "生科領漲、軟體重挫，資金選擇性風險偏好，台股強勢領跑",
  "regime": "rotation",
  "sectorRotation": {
    "into": [
      "IBB",
      "XLE",
      "2337.TW",
      "2360.TW"
    ],
    "outOf": [
      "IGV",
      "GDX",
      "LUNR",
      "COMP"
    ]
  },
  "tomorrowWatch": "監控2337.TW三星共振訊號與收益率4.49%對風險資產後續壓力"
}