{
  "scannedAt": "2026-06-30T21:21:20.462Z",
  "universeSize": 1213,
  "scannedCount": 1213,
  "passedCount": 436,
  "benchmark": {
    "symbol": "SPY",
    "ret12_1": 22.81
  },
  "leaders": [
    {
      "symbol": "STTK",
      "name": "Shattuck Labs, Inc.",
      "price": 6.94,
      "changePct": 1.31,
      "ret1m": 22.83,
      "ret3m": 7.93,
      "ret6m": 98.29,
      "ret12_1": 592.4,
      "rs12_1": 569.59,
      "sector": "Healthcare",
      "industry": "Biotechnology",
      "sectorEtf": "IBB",
      "sectorRS": 559.7,
      "accel": 5,
      "volExpand": 2,
      "volTrend": 1.52,
      "ma50": 6.07,
      "avgVol20": 1901044,
      "high52w": 8.33,
      "high3m": 8.33,
      "vcpScore": 0,
      "vcpDepth": null,
      "vcpBaseNumber": 0,
      "vcpPivot": null,
      "vcpBaseDays": 0,
      "vcpPriorPullbackPct": null,
      "qlibScore": 44,
      "qlibSubs": {
        "kmid": 31,
        "breakout": 0,
        "roc20": 79,
        "contract": 0,
        "volExp": 99,
        "chip": 67,
        "align": 74,
        "accel": 0
      },
      "isLeader": true,
      "isDiscovery": false,
      "earningsDate": 1778112000,
      "daysToEarnings": -54,
      "shortPctOfFloat": 0.0276,
      "shortRatio": 2.52,
      "recentUpgrades": [
        {
          "firm": "Citigroup",
          "action": "up",
          "date": "2026-06-05"
        }
      ],
      "recentDowngrades": [
        {
          "firm": "HC Wainwright & Co.",
          "action": "reit",
          "date": "2026-06-08"
        }
      ],
      "surpriseHistory": [
        {
          "qtr": "2025-06-30 00:00:00",
          "actual": -0.24,
          "estimate": -0.245,
          "surprisePct": 0.020399999
        },
        {
          "qtr": "2025-09-30 00:00:00",
          "actual": -0.14,
          "estimate": -0.14593,
          "surprisePct": 0.040599998
        },
        {
          "qtr": "2025-12-31 00:00:00",
          "actual": -0.12,
          "estimate": -0.13489,
          "surprisePct": 0.1104
        },
        {
          "qtr": "2026-03-31 00:00:00",
          "actual": -0.13,
          "estimate": -0.132,
          "surprisePct": 0.0152
        }
      ],
      "recommendation": {
        "strongBuy": 2,
        "buy": 6,
        "hold": 0,
        "sell": 0,
        "strongSell": 0
      },
      "rsRating": 97,
      "compositeScore": 91,
      "epsRevision": {
        "current": -0.5005,
        "pct90d": 3.08,
        "pct30d": -8.17,
        "pct7d": 0
      },
      "epsRevisionCounts": {
        "up7d": 0,
        "up30d": 0,
        "down7d": 3,
        "down30d": 3
      }
    },
    {
      "symbol": "CAMP",
      "name": "CAMP4 THERAPEUTICS CORPORATION",
      "price": 4.37,
      "changePct": -1.58,
      "ret1m": 8.17,
      "ret3m": -0.91,
      "ret6m": -27.05,
      "ret12_1": 199.26,
      "rs12_1": 176.45,
      "sector": "Healthcare",
      "industry": "Biotechnology",
      "sectorEtf": "IBB",
      "sectorRS": 166.56,
      "accel": null,
      "volExpand": 2.62,
      "volTrend": 1.61,
      "ma50": 4.26,
      "avgVol20": 322612,
      "high52w": 7.75,
      "high3m": 5.25,
      "vcpScore": 0,
      "vcpDepth": null,
      "vcpBaseNumber": 0,
      "vcpPivot": null,
      "vcpBaseDays": 0,
      "vcpPriorPullbackPct": null,
      "qlibScore": 35,
      "qlibSubs": {
        "kmid": 19,
        "breakout": 0,
        "roc20": 37,
        "contract": 24,
        "volExp": 48,
        "chip": 99,
        "align": 50,
        "accel": 0
      },
      "isLeader": true,
      "isDiscovery": false,
      "earningsDate": null,
      "daysToEarnings": null,
      "shortPctOfFloat": 0.0113,
      "shortRatio": 5.68,
      "recentUpgrades": [
        {
          "firm": "JP Morgan",
          "action": "up",
          "date": "2026-06-16"
        },
        {
          "firm": "Chardan Capital",
          "action": "init",
          "date": "2026-06-10"
        }
      ],
      "recentDowngrades": [],
      "surpriseHistory": [
        {
          "qtr": "2025-06-30 00:00:00",
          "actual": -0.62,
          "estimate": -0.67254,
          "surprisePct": 0.078099996
        },
        {
          "qtr": "2025-09-30 00:00:00",
          "actual": -0.5355,
          "estimate": -0.47863,
          "surprisePct": -0.1188
        },
        {
          "qtr": "2025-12-31 00:00:00",
          "actual": -0.2258,
          "estimate": -0.28831,
          "surprisePct": 0.2168
        },
        {
          "qtr": "2026-03-31 00:00:00",
          "actual": -0.2096,
          "estimate": -0.20667,
          "surprisePct": -0.014199999
        }
      ],
      "recommendation": {
        "strongBuy": 2,
        "buy": 5,
        "hold": 0,
        "sell": 0,
        "strongSell": 0
      },
      "rsRating": 87,
      "compositeScore": 89,
      "epsRevision": {
        "current": -0.7932,
        "pct90d": -3.46,
        "pct30d": -3.11,
        "pct7d": 0
      },
      "epsRevisionCounts": {
        "up7d": 1,
        "up30d": 1,
        "down7d": 2,
        "down30d": 2
      }
    },
    {
      "symbol": "ARWR",
      "name": "Arrowhead Pharmaceuticals, Inc.",
      "price": 81.51,
      "changePct": 1.25,
      "ret1m": 8.39,
      "ret3m": 30,
      "ret6m": 17.08,
      "ret12_1": 367.37,
      "rs12_1": 344.56,
      "sector": "Healthcare",
      "industry": "Biotechnology",
      "sectorEtf": "IBB",
      "sectorRS": 334.67,
      "accel": 0.84,
      "volExpand": 2.13,
      "volTrend": 1.2,
      "ma50": 75.97,
      "avgVol20": 2609689,
      "high52w": 84.55,
      "high3m": 84.55,
      "vcpScore": 4,
      "vcpDepth": 15,
      "vcpBaseNumber": 2,
      "vcpPivot": 84.55,
      "vcpBaseDays": 12,
      "vcpPriorPullbackPct": 10.9,
      "qlibScore": 42,
      "qlibSubs": {
        "kmid": 49,
        "breakout": 75,
        "roc20": 38,
        "contract": 41,
        "volExp": 28,
        "chip": 32,
        "align": 74,
        "accel": 0
      },
      "isLeader": true,
      "isDiscovery": false,
      "earningsDate": 1785974400,
      "daysToEarnings": 37,
      "shortPctOfFloat": 0.1161,
      "shortRatio": 7.88,
      "recentUpgrades": [],
      "recentDowngrades": [],
      "surpriseHistory": [
        {
          "qtr": "2025-06-30 00:00:00",
          "actual": -1.26,
          "estimate": -1.10134,
          "surprisePct": -0.1441
        },
        {
          "qtr": "2025-09-30 00:00:00",
          "actual": -0.18,
          "estimate": -0.15727,
          "surprisePct": -0.1445
        },
        {
          "qtr": "2025-12-31 00:00:00",
          "actual": 0.22,
          "estimate": -0.3675,
          "surprisePct": 1.5986
        },
        {
          "qtr": "2026-03-31 00:00:00",
          "actual": -0.93,
          "estimate": -1.10683,
          "surprisePct": 0.1598
        }
      ],
      "recommendation": {
        "strongBuy": 4,
        "buy": 7,
        "hold": 2,
        "sell": 0,
        "strongSell": 0
      },
      "rsRating": 94,
      "compositeScore": 88,
      "epsRevision": {
        "current": -3.0018,
        "pct90d": 7.33,
        "pct30d": 0.04,
        "pct7d": 0.03
      },
      "epsRevisionCounts": {
        "up7d": 1,
        "up30d": 7,
        "down7d": 0,
        "down30d": 3
      }
    },
    {
      "symbol": "XFOR",
      "name": "X4 Pharmaceuticals, Inc.",
      "price": 4.67,
      "changePct": 10.4,
      "ret1m": 13.63,
      "ret3m": 13.08,
      "ret6m": 8.6,
      "ret12_1": 120.97,
      "rs12_1": 98.16,
      "sector": "Healthcare",
      "industry": "Biotechnology",
      "sectorEtf": "IBB",
      "sectorRS": 88.26,
      "accel": 3.13,
      "volExpand": 2.65,
      "volTrend": 1.47,
      "ma50": 4.09,
      "avgVol20": 1019315,
      "high52w": 4.83,
      "high3m": 4.7,
      "vcpScore": 0,
      "vcpDepth": null,
      "vcpBaseNumber": 0,
      "vcpPivot": null,
      "vcpBaseDays": 0,
      "vcpPriorPullbackPct": null,
      "qlibScore": 62,
      "qlibSubs": {
        "kmid": 50,
        "breakout": 95,
        "roc20": 53,
        "contract": 30,
        "volExp": 94,
        "chip": 99,
        "align": 74,
        "accel": 0
      },
      "isLeader": true,
      "isDiscovery": false,
      "earningsDate": 1785974400,
      "daysToEarnings": 37,
      "shortPctOfFloat": 0.0444,
      "shortRatio": 10.42,
      "recentUpgrades": [
        {
          "firm": "Leerink Partners",
          "action": "init",
          "date": "2026-06-02"
        }
      ],
      "recentDowngrades": [],
      "surpriseHistory": [
        {
          "qtr": "2025-06-30 00:00:00",
          "actual": -3.47,
          "estimate": -4.33667,
          "surprisePct": 0.1998
        },
        {
          "qtr": "2025-09-30 00:00:00",
          "actual": -0.69,
          "estimate": -0.84333,
          "surprisePct": 0.18180001
        },
        {
          "qtr": "2025-12-31 00:00:00",
          "actual": -0.22,
          "estimate": -0.3475,
          "surprisePct": 0.3669
        },
        {
          "qtr": "2026-03-31 00:00:00",
          "actual": -0.16,
          "estimate": -0.2,
          "surprisePct": 0.2
        }
      ],
      "recommendation": {
        "strongBuy": 0,
        "buy": 4,
        "hold": 0,
        "sell": 0,
        "strongSell": 0
      },
      "rsRating": 79,
      "compositeScore": 88,
      "epsRevision": {
        "current": -0.755,
        "pct90d": 30.52,
        "pct30d": 13.55,
        "pct7d": 3.21
      },
      "epsRevisionCounts": {
        "up7d": 3,
        "up30d": 2,
        "down7d": 0,
        "down30d": 0
      }
    },
    {
      "symbol": "NUVB",
      "name": "Nuvation Bio Inc.",
      "price": 5.68,
      "changePct": 1.25,
      "ret1m": 14.52,
      "ret3m": 32.4,
      "ret6m": -37.31,
      "ret12_1": 155.67,
      "rs12_1": 132.86,
      "sector": "Healthcare",
      "industry": "Biotechnology",
      "sectorEtf": "IBB",
      "sectorRS": null,
      "accel": 1.34,
      "volExpand": 2.25,
      "volTrend": 1.28,
      "ma50": 4.94,
      "avgVol20": 8271617,
      "high52w": 9.75,
      "high3m": 6.6,
      "vcpScore": 0,
      "vcpDepth": null,
      "vcpBaseNumber": 0,
      "vcpPivot": null,
      "vcpBaseDays": 0,
      "vcpPriorPullbackPct": null,
      "qlibScore": 39,
      "qlibSubs": {
        "kmid": 57,
        "breakout": 7,
        "roc20": 55,
        "contract": 17,
        "volExp": 75,
        "chip": 24,
        "align": 74,
        "accel": 0
      },
      "isLeader": true,
      "isDiscovery": true,
      "earningsDate": 1777852800,
      "daysToEarnings": -57,
      "shortPctOfFloat": 0.2326,
      "shortRatio": 10.53,
      "recentUpgrades": [],
      "recentDowngrades": [],
      "surpriseHistory": [
        {
          "qtr": "2025-06-30 00:00:00",
          "actual": -0.1379,
          "estimate": -0.14,
          "surprisePct": 0.015
        },
        {
          "qtr": "2025-09-30 00:00:00",
          "actual": -0.1395,
          "estimate": -0.15,
          "surprisePct": 0.07
        },
        {
          "qtr": "2025-12-31 00:00:00",
          "actual": -0.086,
          "estimate": -0.045,
          "surprisePct": -0.91110003
        },
        {
          "qtr": "2026-03-31 00:00:00",
          "actual": 0.0382,
          "estimate": 0.05,
          "surprisePct": -0.236
        }
      ],
      "recommendation": {
        "strongBuy": 2,
        "buy": 7,
        "hold": 1,
        "sell": 0,
        "strongSell": 0
      },
      "rsRating": 83,
      "compositeScore": 87,
      "epsRevision": {
        "current": -0.28,
        "pct90d": -150.91,
        "pct30d": -27.27,
        "pct7d": -16.67
      },
      "epsRevisionCounts": {
        "up7d": 0,
        "up30d": 0,
        "down7d": 1,
        "down30d": 1
      }
    },
    {
      "symbol": "FORM",
      "name": "FormFactor, Inc.",
      "price": 159.93,
      "changePct": 10.93,
      "ret1m": 38.98,
      "ret3m": 64.89,
      "ret6m": 178.53,
      "ret12_1": 229.43,
      "rs12_1": 206.62,
      "sector": "Technology",
      "industry": "Semiconductor Equipment & Materials",
      "sectorEtf": "SMH",
      "sectorRS": null,
      "accel": 1.8,
      "volExpand": 1.82,
      "volTrend": 0.97,
      "ma50": 135.97,
      "avgVol20": 1977279,
      "high52w": 160.27,
      "high3m": 160.27,
      "vcpScore": 0,
      "vcpDepth": null,
      "vcpBaseNumber": 0,
      "vcpPivot": null,
      "vcpBaseDays": 0,
      "vcpPriorPullbackPct": null,
      "qlibScore": 55,
      "qlibSubs": {
        "kmid": 39,
        "breakout": 98,
        "roc20": 99,
        "contract": 3,
        "volExp": 17,
        "chip": 60,
        "align": 74,
        "accel": 46
      },
      "isLeader": true,
      "isDiscovery": true,
      "earningsDate": 1785283200,
      "daysToEarnings": 29,
      "shortPctOfFloat": 0.0592,
      "shortRatio": 1.99,
      "recentUpgrades": [
        {
          "firm": "B. Riley Securities",
          "action": "up",
          "date": "2026-06-12"
        },
        {
          "firm": "Evercore ISI Group",
          "action": "up",
          "date": "2026-06-05"
        }
      ],
      "recentDowngrades": [],
      "surpriseHistory": [
        {
          "qtr": "2025-06-30 00:00:00",
          "actual": 0.27,
          "estimate": 0.3,
          "surprisePct": -0.1
        },
        {
          "qtr": "2025-09-30 00:00:00",
          "actual": 0.33,
          "estimate": 0.24857,
          "surprisePct": 0.32759997
        },
        {
          "qtr": "2025-12-31 00:00:00",
          "actual": 0.46,
          "estimate": 0.35222,
          "surprisePct": 0.306
        },
        {
          "qtr": "2026-03-31 00:00:00",
          "actual": 0.56,
          "estimate": 0.43889,
          "surprisePct": 0.2759
        }
      ],
      "recommendation": {
        "strongBuy": 0,
        "buy": 5,
        "hold": 5,
        "sell": 0,
        "strongSell": 0
      },
      "rsRating": 90,
      "compositeScore": 86,
      "epsRevision": {
        "current": 2.4371,
        "pct90d": 31.42,
        "pct30d": 0,
        "pct7d": 0
      },
      "epsRevisionCounts": {
        "up7d": 5,
        "up30d": 5,
        "down7d": 0,
        "down30d": 0
      }
    },
    {
      "symbol": "COGT",
      "name": "Cogent Biosciences, Inc.",
      "price": 38.7,
      "changePct": -0.1,
      "ret1m": 11.17,
      "ret3m": 0.55,
      "ret6m": 2.06,
      "ret12_1": 382.13,
      "rs12_1": 359.32,
      "sector": "Healthcare",
      "industry": "Biotechnology",
      "sectorEtf": "IBB",
      "sectorRS": 349.43,
      "accel": null,
      "volExpand": 1.63,
      "volTrend": 1.25,
      "ma50": 34.69,
      "avgVol20": 3272164,
      "high52w": 43.73,
      "high3m": 40.09,
      "vcpScore": 4,
      "vcpDepth": 16,
      "vcpBaseNumber": 1,
      "vcpPivot": 40.09,
      "vcpBaseDays": 7,
      "vcpPriorPullbackPct": 3.5,
      "qlibScore": 49,
      "qlibSubs": {
        "kmid": 36,
        "breakout": 76,
        "roc20": 46,
        "contract": 46,
        "volExp": 43,
        "chip": 74,
        "align": 74,
        "accel": 0
      },
      "isLeader": true,
      "isDiscovery": false,
      "earningsDate": 1785801600,
      "daysToEarnings": 35,
      "shortPctOfFloat": 0.0792,
      "shortRatio": 5.69,
      "recentUpgrades": [],
      "recentDowngrades": [],
      "surpriseHistory": [
        {
          "qtr": "2025-06-30 00:00:00",
          "actual": -0.53,
          "estimate": -0.57552,
          "surprisePct": 0.0791
        },
        {
          "qtr": "2025-09-30 00:00:00",
          "actual": -0.5,
          "estimate": -0.51673,
          "surprisePct": 0.0324
        },
        {
          "qtr": "2025-12-31 00:00:00",
          "actual": -0.5628,
          "estimate": -0.50929,
          "surprisePct": -0.105100006
        },
        {
          "qtr": "2026-03-31 00:00:00",
          "actual": -0.53,
          "estimate": -0.54016,
          "surprisePct": 0.0188
        }
      ],
      "recommendation": {
        "strongBuy": 2,
        "buy": 9,
        "hold": 2,
        "sell": 0,
        "strongSell": 0
      },
      "rsRating": 95,
      "compositeScore": 84,
      "epsRevision": {
        "current": -2.2561,
        "pct90d": -4.96,
        "pct30d": 0.13,
        "pct7d": 0
      },
      "epsRevisionCounts": {
        "up7d": 0,
        "up30d": 2,
        "down7d": 1,
        "down30d": 7
      }
    },
    {
      "symbol": "IRWD",
      "name": "Ironwood Pharmaceuticals, Inc.",
      "price": 4.21,
      "changePct": -2.09,
      "ret1m": 21.68,
      "ret3m": 19.94,
      "ret6m": 31.15,
      "ret12_1": 394.29,
      "rs12_1": 371.48,
      "sector": "Healthcare",
      "industry": "Drug Manufacturers - Specialty & Generic",
      "sectorEtf": "XLV",
      "sectorRS": 386.14,
      "accel": 3.26,
      "volExpand": 1.36,
      "volTrend": 0.93,
      "ma50": 3.86,
      "avgVol20": 2441272,
      "high52w": 5.78,
      "high3m": 4.88,
      "vcpScore": 4,
      "vcpDepth": 16,
      "vcpBaseNumber": 1,
      "vcpPivot": 4.36,
      "vcpBaseDays": 6,
      "vcpPriorPullbackPct": 6.7,
      "qlibScore": 49,
      "qlibSubs": {
        "kmid": 46,
        "breakout": 8,
        "roc20": 75,
        "contract": 27,
        "volExp": 10,
        "chip": 56,
        "align": 74,
        "accel": 99
      },
      "isLeader": true,
      "isDiscovery": false,
      "earningsDate": 1785974400,
      "daysToEarnings": 37,
      "shortPctOfFloat": 0.105500005,
      "shortRatio": 7.18,
      "recentUpgrades": [],
      "recentDowngrades": [],
      "surpriseHistory": [
        {
          "qtr": "2025-06-30 00:00:00",
          "actual": 0.14,
          "estimate": 0.04,
          "surprisePct": 2.5
        },
        {
          "qtr": "2025-09-30 00:00:00",
          "actual": 0.24,
          "estimate": 0.115,
          "surprisePct": 1.087
        },
        {
          "qtr": "2025-12-31 00:00:00",
          "actual": -0.01,
          "estimate": 0.01,
          "surprisePct": -2
        },
        {
          "qtr": "2026-03-31 00:00:00",
          "actual": 0.24,
          "estimate": 0.24,
          "surprisePct": 0
        }
      ],
      "recommendation": {
        "strongBuy": 1,
        "buy": 1,
        "hold": 2,
        "sell": 0,
        "strongSell": 0
      },
      "rsRating": 96,
      "compositeScore": 84,
      "epsRevision": {
        "current": 1.09,
        "pct90d": 27.73,
        "pct30d": -19.26,
        "pct7d": -19.26
      },
      "epsRevisionCounts": {
        "up7d": 0,
        "up30d": 0,
        "down7d": 1,
        "down30d": 1
      }
    },
    {
      "symbol": "KOD",
      "name": "Kodiak Sciences Inc",
      "price": 38.96,
      "changePct": 3.23,
      "ret1m": 5.55,
      "ret3m": 2.2,
      "ret6m": 35.23,
      "ret12_1": 881.65,
      "rs12_1": 858.84,
      "sector": "Healthcare",
      "industry": "Biotechnology",
      "sectorEtf": "IBB",
      "sectorRS": 848.95,
      "accel": null,
      "volExpand": 1.47,
      "volTrend": 1.18,
      "ma50": 38.13,
      "avgVol20": 917831,
      "high52w": 47.84,
      "high3m": 47.84,
      "vcpScore": 4,
      "vcpDepth": 18,
      "vcpBaseNumber": 1,
      "vcpPivot": 39.39,
      "vcpBaseDays": 8,
      "vcpPriorPullbackPct": 11.9,
      "qlibScore": 27,
      "qlibSubs": {
        "kmid": 32,
        "breakout": 0,
        "roc20": 30,
        "contract": 17,
        "volExp": 3,
        "chip": 63,
        "align": 74,
        "accel": 0
      },
      "isLeader": true,
      "isDiscovery": false,
      "earningsDate": 1778112000,
      "daysToEarnings": -54,
      "shortPctOfFloat": 0.2656,
      "shortRatio": 14.76,
      "recentUpgrades": [],
      "recentDowngrades": [],
      "surpriseHistory": [
        {
          "qtr": "2025-06-30 00:00:00",
          "actual": -1.03,
          "estimate": -1.04674,
          "surprisePct": 0.016
        },
        {
          "qtr": "2025-09-30 00:00:00",
          "actual": -1.16,
          "estimate": -1.04061,
          "surprisePct": -0.114700004
        },
        {
          "qtr": "2025-12-31 00:00:00",
          "actual": -1.04,
          "estimate": -1.05315,
          "surprisePct": 0.0125
        },
        {
          "qtr": "2026-03-31 00:00:00",
          "actual": -0.94,
          "estimate": -1.01146,
          "surprisePct": 0.070700005
        }
      ],
      "recommendation": {
        "strongBuy": 1,
        "buy": 6,
        "hold": 0,
        "sell": 0,
        "strongSell": 0
      },
      "rsRating": 99,
      "compositeScore": 84,
      "epsRevision": {
        "current": -3.7418,
        "pct90d": -0.41,
        "pct30d": 7.78,
        "pct7d": 7.78
      },
      "epsRevisionCounts": {
        "up7d": 4,
        "up30d": 4,
        "down7d": 0,
        "down30d": 0
      }
    },
    {
      "symbol": "ZNTL",
      "name": "Zentalis Pharmaceuticals, Inc.",
      "price": 4.85,
      "changePct": 5.21,
      "ret1m": 21.86,
      "ret3m": 107.26,
      "ret6m": 256.62,
      "ret12_1": 234.45,
      "rs12_1": 211.64,
      "sector": "Healthcare",
      "industry": "Biotechnology",
      "sectorEtf": "IBB",
      "sectorRS": 201.75,
      "accel": 0.61,
      "volExpand": 2.13,
      "volTrend": 1.19,
      "ma50": 3.95,
      "avgVol20": 1378750,
      "high52w": 6.95,
      "high3m": 6.95,
      "vcpScore": 0,
      "vcpDepth": null,
      "vcpBaseNumber": 0,
      "vcpPivot": null,
      "vcpBaseDays": 0,
      "vcpPriorPullbackPct": null,
      "qlibScore": 45,
      "qlibSubs": {
        "kmid": 99,
        "breakout": 0,
        "roc20": 76,
        "contract": 15,
        "volExp": 0,
        "chip": 99,
        "align": 74,
        "accel": 0
      },
      "isLeader": true,
      "isDiscovery": false,
      "earningsDate": 1785974400,
      "daysToEarnings": 37,
      "shortPctOfFloat": 0.0876,
      "shortRatio": 5.34,
      "recentUpgrades": [],
      "recentDowngrades": [],
      "surpriseHistory": [
        {
          "qtr": "2025-06-30 00:00:00",
          "actual": -0.37,
          "estimate": -0.52286,
          "surprisePct": 0.2924
        },
        {
          "qtr": "2025-09-30 00:00:00",
          "actual": -0.37,
          "estimate": -0.47714,
          "surprisePct": 0.2245
        },
        {
          "qtr": "2025-12-31 00:00:00",
          "actual": -0.49,
          "estimate": -0.61143,
          "surprisePct": 0.19860001
        },
        {
          "qtr": "2026-03-31 00:00:00",
          "actual": null,
          "estimate": -0.52333,
          "surprisePct": null
        }
      ],
      "recommendation": {
        "strongBuy": 0,
        "buy": 4,
        "hold": 5,
        "sell": 0,
        "strongSell": 0
      },
      "rsRating": 90,
      "compositeScore": 83,
      "epsRevision": {
        "current": -1.736,
        "pct90d": 4.84,
        "pct30d": 0,
        "pct7d": 0
      },
      "epsRevisionCounts": {
        "up7d": 0,
        "up30d": 0,
        "down7d": 1,
        "down30d": 1
      }
    },
    {
      "symbol": "MGNX",
      "name": "MacroGenics, Inc.",
      "price": 4.62,
      "changePct": -4.94,
      "ret1m": 11.59,
      "ret3m": 59.86,
      "ret6m": 188.75,
      "ret12_1": 228.57,
      "rs12_1": 205.76,
      "sector": "Healthcare",
      "industry": "Biotechnology",
      "sectorEtf": "IBB",
      "sectorRS": 195.87,
      "accel": 0.58,
      "volExpand": 2.19,
      "volTrend": 0.9,
      "ma50": 3.88,
      "avgVol20": 1259856,
      "high52w": 5.08,
      "high3m": 5.08,
      "vcpScore": 3,
      "vcpDepth": 12,
      "vcpBaseNumber": 3,
      "vcpPivot": 5.08,
      "vcpBaseDays": 6,
      "vcpPriorPullbackPct": 1.8,
      "qlibScore": 42,
      "qlibSubs": {
        "kmid": 46,
        "breakout": 39,
        "roc20": 47,
        "contract": 24,
        "volExp": 9,
        "chip": 99,
        "align": 74,
        "accel": 0
      },
      "isLeader": true,
      "isDiscovery": false,
      "earningsDate": 1786579200,
      "daysToEarnings": 44,
      "shortPctOfFloat": 0.078099996,
      "shortRatio": 5.94,
      "recentUpgrades": [],
      "recentDowngrades": [],
      "surpriseHistory": [
        {
          "qtr": "2025-06-30 00:00:00",
          "actual": -0.57,
          "estimate": 0.38,
          "surprisePct": -2.5
        },
        {
          "qtr": "2025-09-30 00:00:00",
          "actual": 0.27,
          "estimate": -0.505,
          "surprisePct": 1.5347
        },
        {
          "qtr": "2025-12-31 00:00:00",
          "actual": -0.22,
          "estimate": -0.02,
          "surprisePct": -10
        },
        {
          "qtr": "2026-03-31 00:00:00",
          "actual": -0.58,
          "estimate": -0.5475,
          "surprisePct": -0.0594
        }
      ],
      "recommendation": {
        "strongBuy": 1,
        "buy": 2,
        "hold": 4,
        "sell": 0,
        "strongSell": 0
      },
      "rsRating": 90,
      "compositeScore": 83,
      "epsRevision": {
        "current": 0.035,
        "pct90d": 102.04,
        "pct30d": 102.03,
        "pct7d": 101.99
      },
      "epsRevisionCounts": {
        "up7d": 0,
        "up30d": 0,
        "down7d": 1,
        "down30d": 1
      }
    },
    {
      "symbol": "GLW",
      "name": "Corning Incorporated",
      "price": 255.43,
      "changePct": -0.1,
      "ret1m": 44.56,
      "ret3m": 87.86,
      "ret6m": 187,
      "ret12_1": 236,
      "rs12_1": 213.18,
      "sector": "Technology",
      "industry": "Electronic Components",
      "sectorEtf": "XLK",
      "sectorRS": null,
      "accel": 1.52,
      "volExpand": 1.56,
      "volTrend": 1.05,
      "ma50": 186.84,
      "avgVol20": 17128254,
      "high52w": 271.78,
      "high3m": 271.78,
      "vcpScore": 0,
      "vcpDepth": null,
      "vcpBaseNumber": 0,
      "vcpPivot": null,
      "vcpBaseDays": 0,
      "vcpPriorPullbackPct": null,
      "qlibScore": 55,
      "qlibSubs": {
        "kmid": 47,
        "breakout": 59,
        "roc20": 99,
        "contract": 3,
        "volExp": 30,
        "chip": 60,
        "align": 99,
        "accel": 41
      },
      "isLeader": true,
      "isDiscovery": true,
      "earningsDate": 1785196800,
      "daysToEarnings": 28,
      "shortPctOfFloat": 0.0312,
      "shortRatio": 1.88,
      "recentUpgrades": [],
      "recentDowngrades": [],
      "surpriseHistory": [
        {
          "qtr": "2025-06-30 00:00:00",
          "actual": 0.6,
          "estimate": 0.57072,
          "surprisePct": 0.0513
        },
        {
          "qtr": "2025-09-30 00:00:00",
          "actual": 0.67,
          "estimate": 0.66471,
          "surprisePct": 0.008
        },
        {
          "qtr": "2025-12-31 00:00:00",
          "actual": 0.72,
          "estimate": 0.70535,
          "surprisePct": 0.0208
        },
        {
          "qtr": "2026-03-31 00:00:00",
          "actual": 0.7,
          "estimate": 0.6916,
          "surprisePct": 0.0121
        }
      ],
      "recommendation": {
        "strongBuy": 0,
        "buy": 11,
        "hold": 4,
        "sell": 0,
        "strongSell": 1
      },
      "rsRating": 90,
      "compositeScore": 83,
      "epsRevision": {
        "current": 3.196,
        "pct90d": 1.76,
        "pct30d": 0.02,
        "pct7d": 0.11
      },
      "epsRevisionCounts": {
        "up7d": 0,
        "up30d": 6,
        "down7d": 1,
        "down30d": 2
      }
    },
    {
      "symbol": "BE",
      "name": "Bloom Energy Corporation",
      "price": 302.7,
      "changePct": 10.07,
      "ret1m": 10.67,
      "ret3m": 123.41,
      "ret6m": 242.38,
      "ret12_1": 1135.92,
      "rs12_1": 1113.11,
      "sector": "Industrials",
      "industry": "Electrical Equipment & Parts",
      "sectorEtf": "XLI",
      "sectorRS": 1119.45,
      "accel": 0.26,
      "volExpand": 1.59,
      "volTrend": 1.16,
      "ma50": 276.89,
      "avgVol20": 13867827,
      "high52w": 351.28,
      "high3m": 351.28,
      "vcpScore": 0,
      "vcpDepth": null,
      "vcpBaseNumber": 0,
      "vcpPivot": null,
      "vcpBaseDays": 0,
      "vcpPriorPullbackPct": null,
      "qlibScore": 33,
      "qlibSubs": {
        "kmid": 50,
        "breakout": 8,
        "roc20": 44,
        "contract": 0,
        "volExp": 30,
        "chip": 57,
        "align": 74,
        "accel": 0
      },
      "isLeader": true,
      "isDiscovery": false,
      "earningsDate": 1777334400,
      "daysToEarnings": -63,
      "shortPctOfFloat": 0.119799994,
      "shortRatio": 2.84,
      "recentUpgrades": [
        {
          "firm": "Bernstein",
          "action": "init",
          "date": "2026-06-17"
        }
      ],
      "recentDowngrades": [],
      "surpriseHistory": [
        {
          "qtr": "2025-06-30 00:00:00",
          "actual": 0.1,
          "estimate": 0.01795,
          "surprisePct": 4.571
        },
        {
          "qtr": "2025-09-30 00:00:00",
          "actual": 0.15,
          "estimate": 0.10201,
          "surprisePct": 0.4704
        },
        {
          "qtr": "2025-12-31 00:00:00",
          "actual": 0.45,
          "estimate": 0.29925,
          "surprisePct": 0.50380003
        },
        {
          "qtr": "2026-03-31 00:00:00",
          "actual": 0.44,
          "estimate": 0.12849,
          "surprisePct": 2.4244
        }
      ],
      "recommendation": {
        "strongBuy": 5,
        "buy": 9,
        "hold": 12,
        "sell": 1,
        "strongSell": 1
      },
      "rsRating": 99,
      "compositeScore": 82,
      "epsRevision": {
        "current": 2.1387,
        "pct90d": 53.41,
        "pct30d": 0.57,
        "pct7d": 0.21
      },
      "epsRevisionCounts": {
        "up7d": 0,
        "up30d": 20,
        "down7d": 0,
        "down30d": 0
      }
    },
    {
      "symbol": "TRVI",
      "name": "Trevi Therapeutics, Inc.",
      "price": 18.65,
      "changePct": 0.11,
      "ret1m": 33.69,
      "ret3m": 56.33,
      "ret6m": 45.48,
      "ret12_1": 144.74,
      "rs12_1": 121.93,
      "sector": "Healthcare",
      "industry": "Biotechnology",
      "sectorEtf": "IBB",
      "sectorRS": null,
      "accel": 1.79,
      "volExpand": 1.81,
      "volTrend": 1.25,
      "ma50": 14.83,
      "avgVol20": 2243171,
      "high52w": 19.26,
      "high3m": 19.26,
      "vcpScore": 3,
      "vcpDepth": 17,
      "vcpBaseNumber": 3,
      "vcpPivot": 19.26,
      "vcpBaseDays": 8,
      "vcpPriorPullbackPct": 1.9,
      "qlibScore": 75,
      "qlibSubs": {
        "kmid": 69,
        "breakout": 78,
        "roc20": 99,
        "contract": 41,
        "volExp": 41,
        "chip": 99,
        "align": 99,
        "accel": 76
      },
      "isLeader": true,
      "isDiscovery": true,
      "earningsDate": 1777939200,
      "daysToEarnings": -56,
      "shortPctOfFloat": 0.11229999,
      "shortRatio": 13.9,
      "recentUpgrades": [],
      "recentDowngrades": [],
      "surpriseHistory": [
        {
          "qtr": "2025-06-30 00:00:00",
          "actual": -0.09,
          "estimate": -0.10125,
          "surprisePct": 0.111099996
        },
        {
          "qtr": "2025-09-30 00:00:00",
          "actual": -0.08,
          "estimate": -0.09889,
          "surprisePct": 0.191
        },
        {
          "qtr": "2025-12-31 00:00:00",
          "actual": -0.06,
          "estimate": -0.09556,
          "surprisePct": 0.3721
        },
        {
          "qtr": "2026-03-31 00:00:00",
          "actual": -0.09,
          "estimate": -0.073,
          "surprisePct": -0.23290001
        }
      ],
      "recommendation": {
        "strongBuy": 2,
        "buy": 8,
        "hold": 0,
        "sell": 0,
        "strongSell": 0
      },
      "rsRating": 82,
      "compositeScore": 82,
      "epsRevision": {
        "current": -0.4689,
        "pct90d": -4.78,
        "pct30d": -9.81,
        "pct7d": -4.43
      },
      "epsRevisionCounts": {
        "up7d": 3,
        "up30d": 3,
        "down7d": 1,
        "down30d": 1
      }
    },
    {
      "symbol": "TTMI",
      "name": "TTM Technologies, Inc.",
      "price": 187.02,
      "changePct": 0.12,
      "ret1m": 8.46,
      "ret3m": 91.97,
      "ret6m": 162.63,
      "ret12_1": 324.52,
      "rs12_1": 301.71,
      "sector": "Technology",
      "industry": "Electronic Components",
      "sectorEtf": "XLK",
      "sectorRS": 268.52,
      "accel": 0.28,
      "volExpand": 1.85,
      "volTrend": 1.05,
      "ma50": 173.44,
      "avgVol20": 2962566,
      "high52w": 223.83,
      "high3m": 223.83,
      "vcpScore": 0,
      "vcpDepth": null,
      "vcpBaseNumber": 0,
      "vcpPivot": null,
      "vcpBaseDays": 0,
      "vcpPriorPullbackPct": null,
      "qlibScore": 27,
      "qlibSubs": {
        "kmid": 39,
        "breakout": 0,
        "roc20": 38,
        "contract": 16,
        "volExp": 31,
        "chip": 44,
        "align": 50,
        "accel": 0
      },
      "isLeader": true,
      "isDiscovery": false,
      "earningsDate": 1785283200,
      "daysToEarnings": 29,
      "shortPctOfFloat": 0.0598,
      "shortRatio": 1.71,
      "recentUpgrades": [],
      "recentDowngrades": [
        {
          "firm": "Needham",
          "action": "reit",
          "date": "2026-06-11"
        }
      ],
      "surpriseHistory": [
        {
          "qtr": "2025-06-30 00:00:00",
          "actual": 0.58,
          "estimate": 0.5225,
          "surprisePct": 0.11
        },
        {
          "qtr": "2025-09-30 00:00:00",
          "actual": 0.67,
          "estimate": 0.6025,
          "surprisePct": 0.111999996
        },
        {
          "qtr": "2025-12-31 00:00:00",
          "actual": 0.7,
          "estimate": 0.6825,
          "surprisePct": 0.0256
        },
        {
          "qtr": "2026-03-31 00:00:00",
          "actual": 0.75,
          "estimate": 0.6675,
          "surprisePct": 0.1236
        }
      ],
      "recommendation": {
        "strongBuy": 1,
        "buy": 3,
        "hold": 0,
        "sell": 0,
        "strongSell": 0
      },
      "rsRating": 93,
      "compositeScore": 82,
      "epsRevision": {
        "current": 4.065,
        "pct90d": 26.64,
        "pct30d": 10.99,
        "pct7d": 0
      },
      "epsRevisionCounts": {
        "up7d": 4,
        "up30d": 4,
        "down7d": 0,
        "down30d": 0
      }
    },
    {
      "symbol": "DOCN",
      "name": "DigitalOcean Holdings, Inc.",
      "price": 157.03,
      "changePct": 4.78,
      "ret1m": -9.47,
      "ret3m": 83.06,
      "ret6m": 218.26,
      "ret12_1": 519.02,
      "rs12_1": 496.21,
      "sector": "Technology",
      "industry": "Software - Infrastructure",
      "sectorEtf": "IGV",
      "sectorRS": 519.52,
      "accel": -0.34,
      "volExpand": 1.55,
      "volTrend": 0.92,
      "ma50": 147.53,
      "avgVol20": 3558152,
      "high52w": 187.5,
      "high3m": 187.5,
      "vcpScore": 1,
      "vcpDepth": 17,
      "vcpBaseNumber": 4,
      "vcpPivot": 160.44,
      "vcpBaseDays": 6,
      "vcpPriorPullbackPct": 27.2,
      "qlibScore": 23,
      "qlibSubs": {
        "kmid": 54,
        "breakout": 0,
        "roc20": 0,
        "contract": 26,
        "volExp": 0,
        "chip": 56,
        "align": 50,
        "accel": 0
      },
      "isLeader": true,
      "isDiscovery": false,
      "earningsDate": 1785801600,
      "daysToEarnings": 35,
      "shortPctOfFloat": 0.15,
      "shortRatio": 4.08,
      "recentUpgrades": [
        {
          "firm": "Keybanc",
          "action": "init",
          "date": "2026-06-03"
        }
      ],
      "recentDowngrades": [],
      "surpriseHistory": [
        {
          "qtr": "2025-06-30 00:00:00",
          "actual": 0.59,
          "estimate": 0.46757,
          "surprisePct": 0.2618
        },
        {
          "qtr": "2025-09-30 00:00:00",
          "actual": 0.54,
          "estimate": 0.49326,
          "surprisePct": 0.094799995
        },
        {
          "qtr": "2025-12-31 00:00:00",
          "actual": 0.44,
          "estimate": 0.3809,
          "surprisePct": 0.1552
        },
        {
          "qtr": "2026-03-31 00:00:00",
          "actual": 0.44,
          "estimate": 0.26241,
          "surprisePct": 0.6768
        }
      ],
      "recommendation": {
        "strongBuy": 3,
        "buy": 8,
        "hold": 4,
        "sell": 0,
        "strongSell": 0
      },
      "rsRating": 97,
      "compositeScore": 81,
      "epsRevision": {
        "current": 1.1957,
        "pct90d": 26.9,
        "pct30d": -0.27,
        "pct7d": 0.0
      },
      "epsRevisionCounts": {
        "up7d": 13,
        "up30d": 14,
        "down7d": 0,
        "down30d": 0
      }
    },
    {
      "symbol": "RCUS",
      "name": "Arcus Biosciences, Inc.",
      "price": 30.83,
      "changePct": -0.8,
      "ret1m": 20.1,
      "ret3m": 42.73,
      "ret6m": 32.15,
      "ret12_1": 207.06,
      "rs12_1": 184.25,
      "sector": "Healthcare",
      "industry": "Biotechnology",
      "sectorEtf": "IBB",
      "sectorRS": null,
      "accel": 1.41,
      "volExpand": 1.39,
      "volTrend": 1.26,
      "ma50": 25.16,
      "avgVol20": 1669316,
      "high52w": 31.74,
      "high3m": 31.74,
      "vcpScore": 4,
      "vcpDepth": 13,
      "vcpBaseNumber": 1,
      "vcpPivot": 31.74,
      "vcpBaseDays": 5,
      "vcpPriorPullbackPct": 1,
      "qlibScore": 72,
      "qlibSubs": {
        "kmid": 65,
        "breakout": 80,
        "roc20": 71,
        "contract": 24,
        "volExp": 37,
        "chip": 99,
        "align": 99,
        "accel": 99
      },
      "isLeader": true,
      "isDiscovery": true,
      "earningsDate": 1785888000,
      "daysToEarnings": 36,
      "shortPctOfFloat": 0.1736,
      "shortRatio": 12.25,
      "recentUpgrades": [
        {
          "firm": "LifeSci Capital",
          "action": "init",
          "date": "2026-06-04"
        }
      ],
      "recentDowngrades": [],
      "surpriseHistory": [
        {
          "qtr": "2025-06-30 00:00:00",
          "actual": 0,
          "estimate": -1.16533,
          "surprisePct": 1
        },
        {
          "qtr": "2025-09-30 00:00:00",
          "actual": -1.27,
          "estimate": -1.29033,
          "surprisePct": 0.015800001
        },
        {
          "qtr": "2025-12-31 00:00:00",
          "actual": -0.89,
          "estimate": -1.075,
          "surprisePct": 0.1721
        },
        {
          "qtr": "2026-03-31 00:00:00",
          "actual": -1.02,
          "estimate": -0.8275,
          "surprisePct": -0.2326
        }
      ],
      "recommendation": {
        "strongBuy": 0,
        "buy": 10,
        "hold": 3,
        "sell": 0,
        "strongSell": 0
      },
      "rsRating": 88,
      "compositeScore": 81,
      "epsRevision": {
        "current": -3.4829,
        "pct90d": 16.08,
        "pct30d": 0.28,
        "pct7d": 1.06
      },
      "epsRevisionCounts": {
        "up7d": 2,
        "up30d": 1,
        "down7d": 2,
        "down30d": 2
      }
    },
    {
      "symbol": "UCTT",
      "name": "Ultra Clean Holdings, Inc.",
      "price": 142.59,
      "changePct": 9.1,
      "ret1m": 68.35,
      "ret3m": 129.32,
      "ret6m": 450.75,
      "ret12_1": 255.88,
      "rs12_1": 233.07,
      "sector": "Technology",
      "industry": "Semiconductor Equipment & Materials",
      "sectorEtf": "SMH",
      "sectorRS": 135.53,
      "accel": 1.59,
      "volExpand": 1.29,
      "volTrend": 1.16,
      "ma50": 92,
      "avgVol20": 1472948,
      "high52w": 144.22,
      "high3m": 144.22,
      "vcpScore": 0,
      "vcpDepth": null,
      "vcpBaseNumber": 0,
      "vcpPivot": null,
      "vcpBaseDays": 0,
      "vcpPriorPullbackPct": null,
      "qlibScore": 69,
      "qlibSubs": {
        "kmid": 64,
        "breakout": 92,
        "roc20": 99,
        "contract": 5,
        "volExp": 35,
        "chip": 68,
        "align": 99,
        "accel": 88
      },
      "isLeader": true,
      "isDiscovery": false,
      "earningsDate": 1785715200,
      "daysToEarnings": 34,
      "shortPctOfFloat": 0.105299994,
      "shortRatio": 2.92,
      "recentUpgrades": [],
      "recentDowngrades": [],
      "surpriseHistory": [
        {
          "qtr": "2025-06-30 00:00:00",
          "actual": 0.27,
          "estimate": 0.27,
          "surprisePct": 0
        },
        {
          "qtr": "2025-09-30 00:00:00",
          "actual": 0.28,
          "estimate": 0.2175,
          "surprisePct": 0.2874
        },
        {
          "qtr": "2025-12-31 00:00:00",
          "actual": 0.22,
          "estimate": 0.225,
          "surprisePct": -0.0222
        },
        {
          "qtr": "2026-03-31 00:00:00",
          "actual": 0.31,
          "estimate": 0.2625,
          "surprisePct": 0.18100001
        }
      ],
      "recommendation": {
        "strongBuy": 1,
        "buy": 4,
        "hold": 0,
        "sell": 0,
        "strongSell": 0
      },
      "rsRating": 91,
      "compositeScore": 81,
      "epsRevision": {
        "current": 2.3475,
        "pct90d": 17.96,
        "pct30d": 1.19,
        "pct7d": 1.19
      },
      "epsRevisionCounts": {
        "up7d": 3,
        "up30d": 3,
        "down7d": 0,
        "down30d": 0
      }
    },
    {
      "symbol": "RVMD",
      "name": "Revolution Medicines, Inc.",
      "price": 187.28,
      "changePct": -2.77,
      "ret1m": 14.42,
      "ret3m": 92.58,
      "ret6m": 132.59,
      "ret12_1": 343.7,
      "rs12_1": 320.89,
      "sector": "Healthcare",
      "industry": "Biotechnology",
      "sectorEtf": "IBB",
      "sectorRS": 310.99,
      "accel": 0.47,
      "volExpand": 1.62,
      "volTrend": 1.11,
      "ma50": 152.87,
      "avgVol20": 3442354,
      "high52w": 193.1,
      "high3m": 193.1,
      "vcpScore": 3,
      "vcpDepth": 16,
      "vcpBaseNumber": 3,
      "vcpPivot": 193.1,
      "vcpBaseDays": 5,
      "vcpPriorPullbackPct": 2.8,
      "qlibScore": 55,
      "qlibSubs": {
        "kmid": 48,
        "breakout": 79,
        "roc20": 55,
        "contract": 34,
        "volExp": 19,
        "chip": 95,
        "align": 99,
        "accel": 7
      },
      "isLeader": true,
      "isDiscovery": false,
      "earningsDate": 1785888000,
      "daysToEarnings": 36,
      "shortPctOfFloat": 0.061,
      "shortRatio": 4.34,
      "recentUpgrades": [],
      "recentDowngrades": [],
      "surpriseHistory": [
        {
          "qtr": "2025-06-30 00:00:00",
          "actual": -1.31,
          "estimate": -1.12213,
          "surprisePct": -0.1674
        },
        {
          "qtr": "2025-09-30 00:00:00",
          "actual": -1.61,
          "estimate": -1.40804,
          "surprisePct": -0.1434
        },
        {
          "qtr": "2025-12-31 00:00:00",
          "actual": -1.86,
          "estimate": -1.56471,
          "surprisePct": -0.1887
        },
        {
          "qtr": "2026-03-31 00:00:00",
          "actual": -2.29,
          "estimate": -1.83771,
          "surprisePct": -0.24610001
        }
      ],
      "recommendation": {
        "strongBuy": 4,
        "buy": 16,
        "hold": 1,
        "sell": 0,
        "strongSell": 0
      },
      "rsRating": 94,
      "compositeScore": 80,
      "epsRevision": {
        "current": -8.0023,
        "pct90d": -5.2,
        "pct30d": -0.45,
        "pct7d": 0.04
      },
      "epsRevisionCounts": {
        "up7d": 1,
        "up30d": 2,
        "down7d": 3,
        "down30d": 16
      }
    },
    {
      "symbol": "TSHA",
      "name": "Taysha Gene Therapies, Inc.",
      "price": 6.81,
      "changePct": 1.19,
      "ret1m": 14.07,
      "ret3m": 52.35,
      "ret6m": 20.53,
      "ret12_1": 155.13,
      "rs12_1": 132.32,
      "sector": "Healthcare",
      "industry": "Biotechnology",
      "sectorEtf": "IBB",
      "sectorRS": 122.42,
      "accel": 0.81,
      "volExpand": 1.88,
      "volTrend": 1.25,
      "ma50": 6.16,
      "avgVol20": 3928710,
      "high52w": 7.3,
      "high3m": 7.3,
      "vcpScore": 4,
      "vcpDepth": 17,
      "vcpBaseNumber": 1,
      "vcpPivot": 7.11,
      "vcpBaseDays": 8,
      "vcpPriorPullbackPct": 4.9,
      "qlibScore": 54,
      "qlibSubs": {
        "kmid": 75,
        "breakout": 55,
        "roc20": 54,
        "contract": 22,
        "volExp": 37,
        "chip": 87,
        "align": 99,
        "accel": 0
      },
      "isLeader": true,
      "isDiscovery": false,
      "earningsDate": 1778025600,
      "daysToEarnings": -55,
      "shortPctOfFloat": 0.1372,
      "shortRatio": 15.84,
      "recentUpgrades": [],
      "recentDowngrades": [],
      "surpriseHistory": [
        {
          "qtr": "2025-06-30 00:00:00",
          "actual": -0.08439,
          "estimate": -0.075,
          "surprisePct": -0.1252
        },
        {
          "qtr": "2025-09-30 00:00:00",
          "actual": -0.08748,
          "estimate": -0.09,
          "surprisePct": 0.027999999
        },
        {
          "qtr": "2025-12-31 00:00:00",
          "actual": -0.07317,
          "estimate": -0.098,
          "surprisePct": 0.2534
        },
        {
          "qtr": "2026-03-31 00:00:00",
          "actual": -0.1117,
          "estimate": -0.098,
          "surprisePct": -0.1398
        }
      ],
      "recommendation": {
        "strongBuy": 3,
        "buy": 10,
        "hold": 0,
        "sell": 0,
        "strongSell": 0
      },
      "rsRating": 83,
      "compositeScore": 80,
      "epsRevision": {
        "current": -0.444,
        "pct90d": -13.27,
        "pct30d": -0.91,
        "pct7d": -0.91
      },
      "epsRevisionCounts": {
        "up7d": 1,
        "up30d": 2,
        "down7d": 0,
        "down30d": 2
      }
    },
    {
      "symbol": "IBRX",
      "name": "ImmunityBio, Inc.",
      "price": 8.76,
      "changePct": -0.17,
      "ret1m": 20.93,
      "ret3m": 14.15,
      "ret6m": 329.17,
      "ret12_1": 181.71,
      "rs12_1": 158.9,
      "sector": "Healthcare",
      "industry": "Biotechnology",
      "sectorEtf": "IBB",
      "sectorRS": 149.01,
      "accel": 4.44,
      "volExpand": 1.42,
      "volTrend": 0.91,
      "ma50": 7.63,
      "avgVol20": 12945746,
      "high52w": 12.43,
      "high3m": 9.08,
      "vcpScore": 0,
      "vcpDepth": null,
      "vcpBaseNumber": 0,
      "vcpPivot": null,
      "vcpBaseDays": 0,
      "vcpPriorPullbackPct": null,
      "qlibScore": 48,
      "qlibSubs": {
        "kmid": 53,
        "breakout": 75,
        "roc20": 73,
        "contract": 26,
        "volExp": 0,
        "chip": 47,
        "align": 74,
        "accel": 38
      },
      "isLeader": true,
      "isDiscovery": false,
      "earningsDate": 1785801600,
      "daysToEarnings": 35,
      "shortPctOfFloat": 0.3479,
      "shortRatio": 9.65,
      "recentUpgrades": [],
      "recentDowngrades": [
        {
          "firm": "HC Wainwright & Co.",
          "action": "reit",
          "date": "2026-06-02"
        }
      ],
      "surpriseHistory": [
        {
          "qtr": "2025-06-30 00:00:00",
          "actual": -0.1,
          "estimate": -0.1,
          "surprisePct": 0
        },
        {
          "qtr": "2025-09-30 00:00:00",
          "actual": -0.07,
          "estimate": -0.1,
          "surprisePct": 0.3
        },
        {
          "qtr": "2025-12-31 00:00:00",
          "actual": -0.06,
          "estimate": -0.09667,
          "surprisePct": 0.3793
        },
        {
          "qtr": "2026-03-31 00:00:00",
          "actual": -0.084,
          "estimate": -0.07,
          "surprisePct": -0.2
        }
      ],
      "recommendation": {
        "strongBuy": 1,
        "buy": 2,
        "hold": 0,
        "sell": 0,
        "strongSell": 0
      },
      "rsRating": 86,
      "compositeScore": 80,
      "epsRevision": {
        "current": -0.85,
        "pct90d": -189.78,
        "pct30d": -220.75,
        "pct7d": -1.8
      },
      "epsRevisionCounts": {
        "up7d": 0,
        "up30d": 0,
        "down7d": 1,
        "down30d": 1
      }
    },
    {
      "symbol": "STOK",
      "name": "Stoke Therapeutics, Inc.",
      "price": 32.72,
      "changePct": 1.02,
      "ret1m": 7.38,
      "ret3m": 0.49,
      "ret6m": 1.68,
      "ret12_1": 161.55,
      "rs12_1": 138.73,
      "sector": "Healthcare",
      "industry": "Biotechnology",
      "sectorEtf": "IBB",
      "sectorRS": 128.84,
      "accel": null,
      "volExpand": 1.82,
      "volTrend": 1.27,
      "ma50": 31.5,
      "avgVol20": 963891,
      "high52w": 40.22,
      "high3m": 37.35,
      "vcpScore": 4,
      "vcpDepth": 15,
      "vcpBaseNumber": 1,
      "vcpPivot": 33.2,
      "vcpBaseDays": 12,
      "vcpPriorPullbackPct": 10.5,
      "qlibScore": 42,
      "qlibSubs": {
        "kmid": 32,
        "breakout": 17,
        "roc20": 35,
        "contract": 44,
        "volExp": 34,
        "chip": 99,
        "align": 74,
        "accel": 0
      },
      "isLeader": true,
      "isDiscovery": false,
      "earningsDate": 1778112000,
      "daysToEarnings": -54,
      "shortPctOfFloat": 0.1958,
      "shortRatio": 20.8,
      "recentUpgrades": [],
      "recentDowngrades": [],
      "surpriseHistory": [
        {
          "qtr": "2025-06-30 00:00:00",
          "actual": -0.4,
          "estimate": -0.5372,
          "surprisePct": 0.2554
        },
        {
          "qtr": "2025-09-30 00:00:00",
          "actual": -0.65,
          "estimate": -0.5742,
          "surprisePct": -0.132
        },
        {
          "qtr": "2025-12-31 00:00:00",
          "actual": -0.97,
          "estimate": -0.736,
          "surprisePct": -0.3179
        },
        {
          "qtr": "2026-03-31 00:00:00",
          "actual": -0.79,
          "estimate": -0.81556,
          "surprisePct": 0.0313
        }
      ],
      "recommendation": {
        "strongBuy": 1,
        "buy": 11,
        "hold": 0,
        "sell": 0,
        "strongSell": 0
      },
      "rsRating": 85,
      "compositeScore": 80,
      "epsRevision": {
        "current": -3.2489,
        "pct90d": -4.62,
        "pct30d": 3.54,
        "pct7d": 3.54
      },
      "epsRevisionCounts": {
        "up7d": 4,
        "up30d": 4,
        "down7d": 2,
        "down30d": 2
      }
    },
    {
      "symbol": "CCCC",
      "name": "C4 Therapeutics, Inc.",
      "price": 4.67,
      "changePct": 7.36,
      "ret1m": 6.62,
      "ret3m": 77.57,
      "ret6m": 130.05,
      "ret12_1": 190.07,
      "rs12_1": 167.26,
      "sector": "Healthcare",
      "industry": "Biotechnology",
      "sectorEtf": "IBB",
      "sectorRS": 157.36,
      "accel": 0.26,
      "volExpand": 2,
      "volTrend": 1.08,
      "ma50": 3.57,
      "avgVol20": 3518360,
      "high52w": 5.17,
      "high3m": 5.17,
      "vcpScore": 0,
      "vcpDepth": null,
      "vcpBaseNumber": 0,
      "vcpPivot": null,
      "vcpBaseDays": 0,
      "vcpPriorPullbackPct": null,
      "qlibScore": 48,
      "qlibSubs": {
        "kmid": 81,
        "breakout": 35,
        "roc20": 33,
        "contract": 20,
        "volExp": 25,
        "chip": 43,
        "align": 99,
        "accel": 45
      },
      "isLeader": true,
      "isDiscovery": false,
      "earningsDate": 1785974400,
      "daysToEarnings": 37,
      "shortPctOfFloat": 0.2025,
      "shortRatio": 9.52,
      "recentUpgrades": [],
      "recentDowngrades": [],
      "surpriseHistory": [
        {
          "qtr": "2025-06-30 00:00:00",
          "actual": -0.37,
          "estimate": -0.3825,
          "surprisePct": 0.0327
        },
        {
          "qtr": "2025-09-30 00:00:00",
          "actual": -0.2954,
          "estimate": -0.392,
          "surprisePct": 0.2464
        },
        {
          "qtr": "2025-12-31 00:00:00",
          "actual": -0.18,
          "estimate": -0.39333,
          "surprisePct": 0.5424
        },
        {
          "qtr": "2026-03-31 00:00:00",
          "actual": -0.2,
          "estimate": -0.26,
          "surprisePct": 0.2308
        }
      ],
      "recommendation": {
        "strongBuy": 1,
        "buy": 6,
        "hold": 0,
        "sell": 0,
        "strongSell": 0
      },
      "rsRating": 87,
      "compositeScore": 80,
      "epsRevision": {
        "current": -0.956,
        "pct90d": 12.83,
        "pct30d": 3.19,
        "pct7d": 0
      },
      "epsRevisionCounts": {
        "up7d": 0,
        "up30d": 1,
        "down7d": 1,
        "down30d": 1
      }
    },
    {
      "symbol": "TNGX",
      "name": "Tango Therapeutics, Inc.",
      "price": 31.26,
      "changePct": -3.99,
      "ret1m": 35.32,
      "ret3m": 49.43,
      "ret6m": 257.26,
      "ret12_1": 324.63,
      "rs12_1": 301.82,
      "sector": "Healthcare",
      "industry": "Biotechnology",
      "sectorEtf": "IBB",
      "sectorRS": 291.93,
      "accel": 2.14,
      "volExpand": 1.06,
      "volTrend": 1.38,
      "ma50": 25.33,
      "avgVol20": 6661669,
      "high52w": 34.39,
      "high3m": 34.39,
      "vcpScore": 0,
      "vcpDepth": null,
      "vcpBaseNumber": 0,
      "vcpPivot": null,
      "vcpBaseDays": 0,
      "vcpPriorPullbackPct": null,
      "qlibScore": 52,
      "qlibSubs": {
        "kmid": 37,
        "breakout": 39,
        "roc20": 99,
        "contract": 0,
        "volExp": 76,
        "chip": 67,
        "align": 99,
        "accel": 0
      },
      "isLeader": true,
      "isDiscovery": false,
      "earningsDate": 1785888000,
      "daysToEarnings": 36,
      "shortPctOfFloat": 0.21149999,
      "shortRatio": 7.02,
      "recentUpgrades": [
        {
          "firm": "Jefferies",
          "action": "up",
          "date": "2026-06-26"
        }
      ],
      "recentDowngrades": [],
      "surpriseHistory": [
        {
          "qtr": "2025-06-30 00:00:00",
          "actual": -0.35,
          "estimate": -0.34338,
          "surprisePct": -0.019299999
        },
        {
          "qtr": "2025-09-30 00:00:00",
          "actual": 0.13,
          "estimate": -0.06938,
          "surprisePct": 2.8737
        },
        {
          "qtr": "2025-12-31 00:00:00",
          "actual": -0.29,
          "estimate": -0.32889,
          "surprisePct": 0.1182
        },
        {
          "qtr": "2026-03-31 00:00:00",
          "actual": -0.32,
          "estimate": -0.31455,
          "surprisePct": -0.0173
        }
      ],
      "recommendation": {
        "strongBuy": 0,
        "buy": 11,
        "hold": 1,
        "sell": 0,
        "strongSell": 0
      },
      "rsRating": 93,
      "compositeScore": 80,
      "epsRevision": {
        "current": -1.3091,
        "pct90d": 0.83,
        "pct30d": 2.23,
        "pct7d": 0.69
      },
      "epsRevisionCounts": {
        "up7d": 1,
        "up30d": 5,
        "down7d": 0,
        "down30d": 4
      }
    },
    {
      "symbol": "STRL",
      "name": "Sterling Infrastructure, Inc.",
      "price": 839.36,
      "changePct": 3.14,
      "ret1m": -0.71,
      "ret3m": 106.09,
      "ret6m": 170.07,
      "ret12_1": 279.88,
      "rs12_1": 257.07,
      "sector": "Industrials",
      "industry": "Engineering & Construction",
      "sectorEtf": "XLI",
      "sectorRS": 263.4,
      "accel": -0.02,
      "volExpand": 1.7,
      "volTrend": 1.07,
      "ma50": 766.22,
      "avgVol20": 923449,
      "high52w": 1005.68,
      "high3m": 1005.68,
      "vcpScore": 4,
      "vcpDepth": 17,
      "vcpBaseNumber": 1,
      "vcpPivot": 925.84,
      "vcpBaseDays": 6,
      "vcpPriorPullbackPct": 21.3,
      "qlibScore": 26,
      "qlibSubs": {
        "kmid": 51,
        "breakout": 0,
        "roc20": 12,
        "contract": 11,
        "volExp": 48,
        "chip": 58,
        "align": 25,
        "accel": 0
      },
      "isLeader": true,
      "isDiscovery": false,
      "earningsDate": 1785715200,
      "daysToEarnings": 34,
      "shortPctOfFloat": 0.0642,
      "shortRatio": 2.53,
      "recentUpgrades": [],
      "recentDowngrades": [],
      "surpriseHistory": [
        {
          "qtr": "2025-06-30 00:00:00",
          "actual": 2.50848,
          "estimate": 2.2525,
          "surprisePct": 0.11359999
        },
        {
          "qtr": "2025-09-30 00:00:00",
          "actual": 3.48,
          "estimate": 2.8375,
          "surprisePct": 0.22639999
        },
        {
          "qtr": "2025-12-31 00:00:00",
          "actual": 3.08,
          "estimate": 2.63167,
          "surprisePct": 0.17040001
        },
        {
          "qtr": "2026-03-31 00:00:00",
          "actual": 3.59,
          "estimate": 2.19,
          "surprisePct": 0.6393
        }
      ],
      "recommendation": {
        "strongBuy": 0,
        "buy": 7,
        "hold": 0,
        "sell": 0,
        "strongSell": 0
      },
      "rsRating": 92,
      "compositeScore": 80,
      "epsRevision": {
        "current": 18.92,
        "pct90d": 39.94,
        "pct30d": 5.09,
        "pct7d": 4.47
      },
      "epsRevisionCounts": {
        "up7d": 5,
        "up30d": 3,
        "down7d": 0,
        "down30d": 0
      }
    }
  ],
  "discoveries": [
    {
      "symbol": "CCXI",
      "name": "Churchill Capital Corp XI",
      "price": 17.45,
      "changePct": 6.4,
      "ret1m": 70.58,
      "ret3m": 71.75,
      "ret6m": null,
      "ret12_1": -0.29,
      "rs12_1": -23.1,
      "sector": "Financial Services",
      "industry": "Shell Companies",
      "sectorEtf": "XLF",
      "sectorRS": 2.04,
      "accel": 2.95,
      "volExpand": 3.99,
      "volTrend": 1.98,
      "ma50": 10.67,
      "avgVol20": 2007882,
      "high52w": 17.5,
      "high3m": 17.5,
      "vcpScore": 0,
      "vcpDepth": null,
      "vcpBaseNumber": 0,
      "vcpPivot": null,
      "vcpBaseDays": 0,
      "vcpPriorPullbackPct": null,
      "qlibScore": 79,
      "qlibSubs": {
        "kmid": 47,
        "breakout": 97,
        "roc20": 99,
        "contract": 13,
        "volExp": 99,
        "chip": 99,
        "align": 99,
        "accel": null
      },
      "isLeader": false,
      "isDiscovery": true,
      "earningsDate": null,
      "daysToEarnings": null,
      "shortPctOfFloat": 0.0001,
      "shortRatio": 0.16,
      "recentUpgrades": [],
      "recentDowngrades": [],
      "surpriseHistory": [],
      "recommendation": null,
      "discoScore": 91,
      "epsRevision": {
        "current": 0,
        "pct90d": null,
        "pct30d": null,
        "pct7d": null
      },
      "epsRevisionCounts": {
        "up7d": 0,
        "up30d": 0,
        "down7d": 0,
        "down30d": 0
      }
    },
    {
      "symbol": "NVCT",
      "name": "Nuvectis Pharma, Inc.",
      "price": 18.39,
      "changePct": -35.54,
      "ret1m": 88.62,
      "ret3m": 137.9,
      "ret6m": 139.45,
      "ret12_1": 33.38,
      "rs12_1": 10.57,
      "sector": "Healthcare",
      "industry": "Biotechnology",
      "sectorEtf": "IBB",
      "sectorRS": null,
      "accel": 1.93,
      "volExpand": 3.11,
      "volTrend": 1.55,
      "ma50": 11.92,
      "avgVol20": 447401,
      "high52w": 29.27,
      "high3m": 29.27,
      "vcpScore": 0,
      "vcpDepth": null,
      "vcpBaseNumber": 0,
      "vcpPivot": null,
      "vcpBaseDays": 0,
      "vcpPriorPullbackPct": null,
      "qlibScore": 60,
      "qlibSubs": {
        "kmid": 99,
        "breakout": 0,
        "roc20": 99,
        "contract": 0,
        "volExp": 99,
        "chip": 45,
        "align": 74,
        "accel": 62
      },
      "isLeader": true,
      "isDiscovery": true,
      "earningsDate": 1785801600,
      "daysToEarnings": 35,
      "shortPctOfFloat": 0.100600004,
      "shortRatio": 16.38,
      "recentUpgrades": [],
      "recentDowngrades": [],
      "surpriseHistory": [
        {
          "qtr": "2025-06-30 00:00:00",
          "actual": -0.3,
          "estimate": -0.25167,
          "surprisePct": -0.192
        },
        {
          "qtr": "2025-09-30 00:00:00",
          "actual": -0.44,
          "estimate": -0.25,
          "surprisePct": -0.76
        },
        {
          "qtr": "2025-12-31 00:00:00",
          "actual": -0.31,
          "estimate": -0.308,
          "surprisePct": -0.0064999997
        },
        {
          "qtr": "2026-03-31 00:00:00",
          "actual": -0.26,
          "estimate": -0.314,
          "surprisePct": 0.172
        }
      ],
      "recommendation": {
        "strongBuy": 2,
        "buy": 3,
        "hold": 0,
        "sell": 0,
        "strongSell": 0
      },
      "rsRating": 44,
      "compositeScore": 66,
      "discoScore": 86,
      "epsRevision": {
        "current": -1.036,
        "pct90d": 18.17,
        "pct30d": 0.96,
        "pct7d": 0.96
      },
      "epsRevisionCounts": {
        "up7d": 2,
        "up30d": 2,
        "down7d": 0,
        "down30d": 0
      }
    },
    {
      "symbol": "PYXS",
      "name": "Pyxis Oncology, Inc.",
      "price": 3.01,
      "changePct": 5.24,
      "ret1m": 68.16,
      "ret3m": 106.16,
      "ret6m": 183.96,
      "ret12_1": 65.74,
      "rs12_1": 42.93,
      "sector": "Healthcare",
      "industry": "Biotechnology",
      "sectorEtf": "IBB",
      "sectorRS": null,
      "accel": 1.93,
      "volExpand": 2.87,
      "volTrend": 1.2,
      "ma50": 1.99,
      "avgVol20": 1152628,
      "high52w": 5.55,
      "high3m": 3.4,
      "vcpScore": 0,
      "vcpDepth": null,
      "vcpBaseNumber": 0,
      "vcpPivot": null,
      "vcpBaseDays": 0,
      "vcpPriorPullbackPct": null,
      "qlibScore": 65,
      "qlibSubs": {
        "kmid": 99,
        "breakout": 23,
        "roc20": 99,
        "contract": 9,
        "volExp": 88,
        "chip": 99,
        "align": 99,
        "accel": 6
      },
      "isLeader": true,
      "isDiscovery": true,
      "earningsDate": 1786579200,
      "daysToEarnings": 44,
      "shortPctOfFloat": 0.043,
      "shortRatio": 3.8,
      "recentUpgrades": [],
      "recentDowngrades": [],
      "surpriseHistory": [
        {
          "qtr": "2025-06-30 00:00:00",
          "actual": -0.3,
          "estimate": -0.35167,
          "surprisePct": 0.1469
        },
        {
          "qtr": "2025-09-30 00:00:00",
          "actual": -0.35,
          "estimate": -0.33857,
          "surprisePct": -0.033800002
        },
        {
          "qtr": "2025-12-31 00:00:00",
          "actual": -0.29,
          "estimate": -0.33889,
          "surprisePct": 0.1443
        },
        {
          "qtr": "2026-03-31 00:00:00",
          "actual": -0.37,
          "estimate": -0.35333,
          "surprisePct": -0.047199998
        }
      ],
      "recommendation": {
        "strongBuy": 1,
        "buy": 7,
        "hold": 1,
        "sell": 0,
        "strongSell": 0
      },
      "rsRating": 67,
      "compositeScore": 80,
      "discoScore": 84,
      "epsRevision": {
        "current": -1.225,
        "pct90d": -3.48,
        "pct30d": 1.3,
        "pct7d": 0.32
      },
      "epsRevisionCounts": {
        "up7d": 4,
        "up30d": 4,
        "down7d": 5,
        "down30d": 4
      }
    },
    {
      "symbol": "TECH",
      "name": "Bio-Techne Corp",
      "price": 70.65,
      "changePct": -0.35,
      "ret1m": 39.1,
      "ret3m": 35.19,
      "ret6m": 19.26,
      "ret12_1": -2.48,
      "rs12_1": -25.29,
      "sector": "Healthcare",
      "industry": "Biotechnology",
      "sectorEtf": "IBB",
      "sectorRS": -35.18,
      "accel": 3.33,
      "volExpand": 2.78,
      "volTrend": 1.33,
      "ma50": 53.52,
      "avgVol20": 7040701,
      "high52w": 72.16,
      "high3m": 71.23,
      "vcpScore": 0,
      "vcpDepth": null,
      "vcpBaseNumber": 0,
      "vcpPivot": null,
      "vcpBaseDays": 0,
      "vcpPriorPullbackPct": null,
      "qlibScore": 65,
      "qlibSubs": {
        "kmid": 36,
        "breakout": 94,
        "roc20": 99,
        "contract": 16,
        "volExp": 99,
        "chip": 77,
        "align": 99,
        "accel": 0
      },
      "isLeader": false,
      "isDiscovery": true,
      "earningsDate": 1785888000,
      "daysToEarnings": 36,
      "shortPctOfFloat": 0.13260001,
      "shortRatio": 5.98,
      "recentUpgrades": [
        {
          "firm": "Piper Sandler",
          "action": "init",
          "date": "2026-06-11"
        }
      ],
      "recentDowngrades": [
        {
          "firm": "TD Cowen",
          "action": "down",
          "date": "2026-06-30"
        },
        {
          "firm": "Benchmark",
          "action": "down",
          "date": "2026-06-30"
        },
        {
          "firm": "Citigroup",
          "action": "down",
          "date": "2026-06-29"
        }
      ],
      "surpriseHistory": [
        {
          "qtr": "2025-06-30 00:00:00",
          "actual": 0.53,
          "estimate": 0.50097,
          "surprisePct": 0.0579
        },
        {
          "qtr": "2025-09-30 00:00:00",
          "actual": 0.42,
          "estimate": 0.4215,
          "surprisePct": -0.0036000002
        },
        {
          "qtr": "2025-12-31 00:00:00",
          "actual": 0.46,
          "estimate": 0.43462,
          "surprisePct": 0.0584
        },
        {
          "qtr": "2026-03-31 00:00:00",
          "actual": 0.53,
          "estimate": 0.53436,
          "surprisePct": -0.0082
        }
      ],
      "recommendation": {
        "strongBuy": 1,
        "buy": 3,
        "hold": 12,
        "sell": 0,
        "strongSell": 0
      },
      "discoScore": 78,
      "epsRevision": {
        "current": 1.9191,
        "pct90d": -3.17,
        "pct30d": -0.04,
        "pct7d": 0
      },
      "epsRevisionCounts": {
        "up7d": 0,
        "up30d": 0,
        "down7d": 1,
        "down30d": 12
      }
    },
    {
      "symbol": "MBX",
      "name": "MBX Biosciences, Inc.",
      "price": 55.2,
      "changePct": 2.51,
      "ret1m": 80.1,
      "ret3m": 84.92,
      "ret6m": 77.66,
      "ret12_1": 164,
      "rs12_1": 141.19,
      "sector": "Healthcare",
      "industry": "Biotechnology",
      "sectorEtf": "IBB",
      "sectorRS": null,
      "accel": 2.83,
      "volExpand": 1.34,
      "volTrend": 1.19,
      "ma50": 35.55,
      "avgVol20": 1080784,
      "high52w": 57.34,
      "high3m": 57.34,
      "vcpScore": 0,
      "vcpDepth": null,
      "vcpBaseNumber": 0,
      "vcpPivot": null,
      "vcpBaseDays": 0,
      "vcpPriorPullbackPct": null,
      "qlibScore": 66,
      "qlibSubs": {
        "kmid": 85,
        "breakout": 74,
        "roc20": 99,
        "contract": 15,
        "volExp": 64,
        "chip": 89,
        "align": 99,
        "accel": 0
      },
      "isLeader": true,
      "isDiscovery": true,
      "earningsDate": 1785974400,
      "daysToEarnings": 37,
      "shortPctOfFloat": 0.1683,
      "shortRatio": 7.25,
      "recentUpgrades": [],
      "recentDowngrades": [],
      "surpriseHistory": [
        {
          "qtr": "2025-06-30 00:00:00",
          "actual": -0.58,
          "estimate": -0.76324,
          "surprisePct": 0.2401
        },
        {
          "qtr": "2025-09-30 00:00:00",
          "actual": -0.63,
          "estimate": -0.67719,
          "surprisePct": 0.069699995
        },
        {
          "qtr": "2025-12-31 00:00:00",
          "actual": -0.49,
          "estimate": -0.59668,
          "surprisePct": 0.17879999
        },
        {
          "qtr": "2026-03-31 00:00:00",
          "actual": -0.51,
          "estimate": -0.58099,
          "surprisePct": 0.122200005
        }
      ],
      "recommendation": {
        "strongBuy": 2,
        "buy": 9,
        "hold": 0,
        "sell": 1,
        "strongSell": 0
      },
      "rsRating": 85,
      "compositeScore": 79,
      "discoScore": 77,
      "epsRevision": {
        "current": -2.7479,
        "pct90d": 5.79,
        "pct30d": 0.0,
        "pct7d": 0.0
      },
      "epsRevisionCounts": {
        "up7d": 7,
        "up30d": 7,
        "down7d": 2,
        "down30d": 2
      }
    },
    {
      "symbol": "AIR",
      "name": "AAR Corp.",
      "price": 142.93,
      "changePct": 0.76,
      "ret1m": 29.95,
      "ret3m": 30.58,
      "ret6m": 69.13,
      "ret12_1": 58.33,
      "rs12_1": 35.52,
      "sector": "Industrials",
      "industry": "Aerospace & Defense",
      "sectorEtf": "XAR",
      "sectorRS": null,
      "accel": 2.94,
      "volExpand": 1.63,
      "volTrend": 1.15,
      "ma50": 117.85,
      "avgVol20": 510757,
      "high52w": 143.46,
      "high3m": 143.46,
      "vcpScore": 4,
      "vcpDepth": 13,
      "vcpBaseNumber": 2,
      "vcpPivot": 143.46,
      "vcpBaseDays": 12,
      "vcpPriorPullbackPct": 0.5,
      "qlibScore": 58,
      "qlibSubs": {
        "kmid": 44,
        "breakout": 97,
        "roc20": 99,
        "contract": 47,
        "volExp": 19,
        "chip": 55,
        "align": 99,
        "accel": 0
      },
      "isLeader": true,
      "isDiscovery": true,
      "earningsDate": null,
      "daysToEarnings": null,
      "shortPctOfFloat": 0.032899998,
      "shortRatio": 3.49,
      "recentUpgrades": [],
      "recentDowngrades": [
        {
          "firm": "Keybanc",
          "action": "down",
          "date": "2026-06-30"
        }
      ],
      "surpriseHistory": [
        {
          "qtr": "2025-05-31 00:00:00",
          "actual": 1.16,
          "estimate": 1.00008,
          "surprisePct": 0.1599
        },
        {
          "qtr": "2025-08-31 00:00:00",
          "actual": 1.08,
          "estimate": 0.984,
          "surprisePct": 0.097600006
        },
        {
          "qtr": "2025-11-30 00:00:00",
          "actual": 1.18,
          "estimate": 1.03333,
          "surprisePct": 0.1419
        },
        {
          "qtr": "2026-02-28 00:00:00",
          "actual": 1.25,
          "estimate": 1.15667,
          "surprisePct": 0.080699995
        }
      ],
      "recommendation": {
        "strongBuy": 1,
        "buy": 5,
        "hold": 1,
        "sell": 0,
        "strongSell": 0
      },
      "rsRating": 64,
      "compositeScore": 65,
      "discoScore": 65,
      "epsRevision": {
        "current": 4.9014,
        "pct90d": 4.13,
        "pct30d": 0.12,
        "pct7d": 0
      },
      "epsRevisionCounts": {
        "up7d": 1,
        "up30d": 1,
        "down7d": 1,
        "down30d": 1
      }
    },
    {
      "symbol": "AMAT",
      "name": "Applied Materials, Inc.",
      "price": 723,
      "changePct": 4.08,
      "ret1m": 57.8,
      "ret3m": 111.53,
      "ret6m": 174.85,
      "ret12_1": 149.33,
      "rs12_1": 126.52,
      "sector": "Technology",
      "industry": "Semiconductor Equipment & Materials",
      "sectorEtf": "SMH",
      "sectorRS": null,
      "accel": 1.55,
      "volExpand": 1.36,
      "volTrend": 1.23,
      "ma50": 480.83,
      "avgVol20": 12463592,
      "high52w": 739.67,
      "high3m": 739.67,
      "vcpScore": 0,
      "vcpDepth": null,
      "vcpBaseNumber": 0,
      "vcpPivot": null,
      "vcpBaseDays": 0,
      "vcpPriorPullbackPct": null,
      "qlibScore": 77,
      "qlibSubs": {
        "kmid": 69,
        "breakout": 84,
        "roc20": 99,
        "contract": 9,
        "volExp": 61,
        "chip": 99,
        "align": 99,
        "accel": 99
      },
      "isLeader": true,
      "isDiscovery": true,
      "earningsDate": 1786579200,
      "daysToEarnings": 44,
      "shortPctOfFloat": 0.0277,
      "shortRatio": 2.51,
      "recentUpgrades": [],
      "recentDowngrades": [],
      "surpriseHistory": [
        {
          "qtr": "2025-07-31 00:00:00",
          "actual": 2.48,
          "estimate": 2.35905,
          "surprisePct": 0.0513
        },
        {
          "qtr": "2025-10-31 00:00:00",
          "actual": 2.17,
          "estimate": 2.09366,
          "surprisePct": 0.0365
        },
        {
          "qtr": "2026-01-31 00:00:00",
          "actual": 2.38,
          "estimate": 2.206,
          "surprisePct": 0.0789
        },
        {
          "qtr": "2026-04-30 00:00:00",
          "actual": 2.86,
          "estimate": 2.68545,
          "surprisePct": 0.065
        }
      ],
      "recommendation": {
        "strongBuy": 4,
        "buy": 28,
        "hold": 6,
        "sell": 0,
        "strongSell": 1
      },
      "rsRating": 83,
      "compositeScore": 78,
      "discoScore": 64,
      "epsRevision": {
        "current": 12.2392,
        "pct90d": 10.77,
        "pct30d": 0.15,
        "pct7d": 0.03
      },
      "epsRevisionCounts": {
        "up7d": 1,
        "up30d": 30,
        "down7d": 0,
        "down30d": 0
      }
    },
    {
      "symbol": "ALGM",
      "name": "Allegro MicroSystems, Inc.",
      "price": 69.62,
      "changePct": 4.9,
      "ret1m": 47.72,
      "ret3m": 120.81,
      "ret6m": 162.42,
      "ret12_1": 37.01,
      "rs12_1": 14.2,
      "sector": "Technology",
      "industry": "Semiconductors",
      "sectorEtf": "SMH",
      "sectorRS": null,
      "accel": 1.19,
      "volExpand": 1.71,
      "volTrend": 1.12,
      "ma50": 49.33,
      "avgVol20": 3473161,
      "high52w": 71.77,
      "high3m": 71.77,
      "vcpScore": 0,
      "vcpDepth": null,
      "vcpBaseNumber": 0,
      "vcpPivot": null,
      "vcpBaseDays": 0,
      "vcpPriorPullbackPct": null,
      "qlibScore": 74,
      "qlibSubs": {
        "kmid": 80,
        "breakout": 79,
        "roc20": 99,
        "contract": 5,
        "volExp": 47,
        "chip": 90,
        "align": 99,
        "accel": 93
      },
      "isLeader": true,
      "isDiscovery": true,
      "earningsDate": 1785369600,
      "daysToEarnings": 30,
      "shortPctOfFloat": 0.1368,
      "shortRatio": 5.94,
      "recentUpgrades": [],
      "recentDowngrades": [],
      "surpriseHistory": [
        {
          "qtr": "2025-06-30 00:00:00",
          "actual": 0.09,
          "estimate": 0.08451,
          "surprisePct": 0.065
        },
        {
          "qtr": "2025-09-30 00:00:00",
          "actual": 0.13,
          "estimate": 0.12337,
          "surprisePct": 0.0537
        },
        {
          "qtr": "2025-12-31 00:00:00",
          "actual": 0.15,
          "estimate": 0.14411,
          "surprisePct": 0.040900003
        },
        {
          "qtr": "2026-03-31 00:00:00",
          "actual": 0.17,
          "estimate": 0.16385,
          "surprisePct": 0.0375
        }
      ],
      "recommendation": {
        "strongBuy": 3,
        "buy": 8,
        "hold": 0,
        "sell": 0,
        "strongSell": 0
      },
      "rsRating": 48,
      "compositeScore": 53,
      "discoScore": 63,
      "epsRevision": {
        "current": 1.0259,
        "pct90d": 8.91,
        "pct30d": -1.87,
        "pct7d": -2.51
      },
      "epsRevisionCounts": {
        "up7d": 6,
        "up30d": 6,
        "down7d": 2,
        "down30d": 2
      }
    },
    {
      "symbol": "VCEL",
      "name": "Vericel Corporation",
      "price": 44.49,
      "changePct": -1.29,
      "ret1m": 35.56,
      "ret3m": 38.3,
      "ret6m": 18.36,
      "ret12_1": -21.11,
      "rs12_1": -43.92,
      "sector": "Healthcare",
      "industry": "Biotechnology",
      "sectorEtf": "IBB",
      "sectorRS": -53.81,
      "accel": 2.79,
      "volExpand": 1.37,
      "volTrend": 1.07,
      "ma50": 36.45,
      "avgVol20": 752077,
      "high52w": 46.62,
      "high3m": 46.62,
      "vcpScore": 4,
      "vcpDepth": 17,
      "vcpBaseNumber": 2,
      "vcpPivot": 46.62,
      "vcpBaseDays": 6,
      "vcpPriorPullbackPct": 2.7,
      "qlibScore": 57,
      "qlibSubs": {
        "kmid": 49,
        "breakout": 69,
        "roc20": 99,
        "contract": 48,
        "volExp": 19,
        "chip": 73,
        "align": 99,
        "accel": 0
      },
      "isLeader": false,
      "isDiscovery": true,
      "earningsDate": 1785369600,
      "daysToEarnings": 30,
      "shortPctOfFloat": 0.13350001,
      "shortRatio": 9.48,
      "recentUpgrades": [],
      "recentDowngrades": [],
      "surpriseHistory": [
        {
          "qtr": "2025-06-30 00:00:00",
          "actual": -0.01,
          "estimate": -0.03667,
          "surprisePct": 0.72730005
        },
        {
          "qtr": "2025-09-30 00:00:00",
          "actual": 0.1,
          "estimate": -0.01333,
          "surprisePct": 8.5019
        },
        {
          "qtr": "2025-12-31 00:00:00",
          "actual": 0.45,
          "estimate": 0.382,
          "surprisePct": 0.17799999
        },
        {
          "qtr": "2026-03-31 00:00:00",
          "actual": -0.12,
          "estimate": -0.15667,
          "surprisePct": 0.2341
        }
      ],
      "recommendation": {
        "strongBuy": 0,
        "buy": 7,
        "hold": 1,
        "sell": 0,
        "strongSell": 0
      },
      "discoScore": 62,
      "epsRevision": {
        "current": 0.452,
        "pct90d": 10.24,
        "pct30d": 0.0,
        "pct7d": 0.0
      },
      "epsRevisionCounts": {
        "up7d": 1,
        "up30d": 1,
        "down7d": 0,
        "down30d": 0
      }
    },
    {
      "symbol": "WTS",
      "name": "Watts Water Technologies, Inc.",
      "price": 391.45,
      "changePct": 9.06,
      "ret1m": 27.52,
      "ret3m": 34.85,
      "ret6m": 38.51,
      "ret12_1": 22.4,
      "rs12_1": -0.42,
      "sector": "Industrials",
      "industry": "Specialty Industrial Machinery",
      "sectorEtf": "XLI",
      "sectorRS": null,
      "accel": 2.37,
      "volExpand": 1.98,
      "volTrend": 1.25,
      "ma50": 314.88,
      "avgVol20": 570233,
      "high52w": 394.54,
      "high3m": 394.54,
      "vcpScore": 2,
      "vcpDepth": 17,
      "vcpBaseNumber": 5,
      "vcpPivot": 394.54,
      "vcpBaseDays": 9,
      "vcpPriorPullbackPct": 1,
      "qlibScore": 76,
      "qlibSubs": {
        "kmid": 47,
        "breakout": 94,
        "roc20": 92,
        "contract": 41,
        "volExp": 78,
        "chip": 59,
        "align": 99,
        "accel": 99
      },
      "isLeader": true,
      "isDiscovery": true,
      "earningsDate": 1785888000,
      "daysToEarnings": 36,
      "shortPctOfFloat": 0.0731,
      "shortRatio": 4.39,
      "recentUpgrades": [
        {
          "firm": "Barclays",
          "action": "up",
          "date": "2026-06-30"
        }
      ],
      "recentDowngrades": [],
      "surpriseHistory": [
        {
          "qtr": "2025-06-30 00:00:00",
          "actual": 3.09,
          "estimate": 2.62534,
          "surprisePct": 0.177
        },
        {
          "qtr": "2025-09-30 00:00:00",
          "actual": 2.5,
          "estimate": 2.26271,
          "surprisePct": 0.104899995
        },
        {
          "qtr": "2025-12-31 00:00:00",
          "actual": 2.62,
          "estimate": 2.3388,
          "surprisePct": 0.12020001
        },
        {
          "qtr": "2026-03-31 00:00:00",
          "actual": 3.04,
          "estimate": 2.68943,
          "surprisePct": 0.1304
        }
      ],
      "recommendation": {
        "strongBuy": 0,
        "buy": 2,
        "hold": 10,
        "sell": 0,
        "strongSell": 0
      },
      "rsRating": 35,
      "compositeScore": 50,
      "discoScore": 62,
      "epsRevision": {
        "current": 11.9445,
        "pct90d": 1.47,
        "pct30d": 1.94,
        "pct7d": 0
      },
      "epsRevisionCounts": {
        "up7d": 8,
        "up30d": 7,
        "down7d": 1,
        "down30d": 1
      }
    },
    {
      "symbol": "AMRX",
      "name": "Amneal Pharmaceuticals, Inc.",
      "price": 17.31,
      "changePct": 0.12,
      "ret1m": 34.19,
      "ret3m": 39.26,
      "ret6m": 34.08,
      "ret12_1": 57.13,
      "rs12_1": 34.31,
      "sector": "Healthcare",
      "industry": "Drug Manufacturers - Specialty & Generic",
      "sectorEtf": "XLV",
      "sectorRS": null,
      "accel": 2.61,
      "volExpand": 1.43,
      "volTrend": 1.22,
      "ma50": 13.91,
      "avgVol20": 2432716,
      "high52w": 17.86,
      "high3m": 17.86,
      "vcpScore": 3,
      "vcpDepth": 6,
      "vcpBaseNumber": 3,
      "vcpPivot": 17.86,
      "vcpBaseDays": 5,
      "vcpPriorPullbackPct": -0.5,
      "qlibScore": 59,
      "qlibSubs": {
        "kmid": 58,
        "breakout": 79,
        "roc20": 99,
        "contract": 46,
        "volExp": 33,
        "chip": 57,
        "align": 99,
        "accel": 0
      },
      "isLeader": true,
      "isDiscovery": true,
      "earningsDate": 1785801600,
      "daysToEarnings": 35,
      "shortPctOfFloat": 0.0382,
      "shortRatio": 4.27,
      "recentUpgrades": [],
      "recentDowngrades": [],
      "surpriseHistory": [
        {
          "qtr": "2025-06-30 00:00:00",
          "actual": 0.25,
          "estimate": 0.17489,
          "surprisePct": 0.4295
        },
        {
          "qtr": "2025-09-30 00:00:00",
          "actual": 0.17,
          "estimate": 0.13834,
          "surprisePct": 0.2289
        },
        {
          "qtr": "2025-12-31 00:00:00",
          "actual": 0.21,
          "estimate": 0.1841,
          "surprisePct": 0.1407
        },
        {
          "qtr": "2026-03-31 00:00:00",
          "actual": 0.27,
          "estimate": 0.16915,
          "surprisePct": 0.5962
        }
      ],
      "recommendation": {
        "strongBuy": 2,
        "buy": 2,
        "hold": 0,
        "sell": 0,
        "strongSell": 0
      },
      "rsRating": 63,
      "compositeScore": 63,
      "discoScore": 61,
      "epsRevision": {
        "current": 0.9871,
        "pct90d": 2.38,
        "pct30d": -0.98,
        "pct7d": -0.38
      },
      "epsRevisionCounts": {
        "up7d": 2,
        "up30d": 2,
        "down7d": 0,
        "down30d": 1
      }
    },
    {
      "symbol": "INMB",
      "name": "INmune Bio Inc.",
      "price": 1.63,
      "changePct": 0.62,
      "ret1m": 17.27,
      "ret3m": 44.25,
      "ret6m": -1.81,
      "ret12_1": -33.49,
      "rs12_1": -56.3,
      "sector": "Healthcare",
      "industry": "Biotechnology",
      "sectorEtf": "IBB",
      "sectorRS": -66.2,
      "accel": 1.17,
      "volExpand": 3.12,
      "volTrend": 1.4,
      "ma50": 1.41,
      "avgVol20": 1146410,
      "high52w": 3.24,
      "high3m": 1.79,
      "vcpScore": 0,
      "vcpDepth": null,
      "vcpBaseNumber": 0,
      "vcpPivot": null,
      "vcpBaseDays": 0,
      "vcpPriorPullbackPct": null,
      "qlibScore": 54,
      "qlibSubs": {
        "kmid": 48,
        "breakout": 40,
        "roc20": 63,
        "contract": 12,
        "volExp": 99,
        "chip": 99,
        "align": 74,
        "accel": 0
      },
      "isLeader": false,
      "isDiscovery": true,
      "earningsDate": 1785974400,
      "daysToEarnings": 37,
      "shortPctOfFloat": 0.1554,
      "shortRatio": 11.28,
      "recentUpgrades": [],
      "recentDowngrades": [],
      "surpriseHistory": [
        {
          "qtr": "2025-06-30 00:00:00",
          "actual": -0.34097,
          "estimate": -0.38,
          "surprisePct": 0.1027
        },
        {
          "qtr": "2025-09-30 00:00:00",
          "actual": -0.24,
          "estimate": -0.325,
          "surprisePct": 0.2615
        },
        {
          "qtr": "2025-12-31 00:00:00",
          "actual": -0.18,
          "estimate": -0.27,
          "surprisePct": 0.33330002
        },
        {
          "qtr": "2026-03-31 00:00:00",
          "actual": -0.2,
          "estimate": -0.18,
          "surprisePct": -0.111099996
        }
      ],
      "recommendation": {
        "strongBuy": 1,
        "buy": 3,
        "hold": 0,
        "sell": 0,
        "strongSell": 0
      },
      "discoScore": 59,
      "epsRevision": {
        "current": -0.6033,
        "pct90d": 22.98,
        "pct30d": 0,
        "pct7d": 0
      },
      "epsRevisionCounts": {
        "up7d": 1,
        "up30d": 2,
        "down7d": 0,
        "down30d": 0
      }
    },
    {
      "symbol": "LGND",
      "name": "Ligand Pharmaceuticals Incorpor",
      "price": 316.09,
      "changePct": 0.65,
      "ret1m": 37.56,
      "ret3m": 58.32,
      "ret6m": 61.96,
      "ret12_1": 104.14,
      "rs12_1": 81.33,
      "sector": "Healthcare",
      "industry": "Biotechnology",
      "sectorEtf": "IBB",
      "sectorRS": null,
      "accel": 1.93,
      "volExpand": 1.5,
      "volTrend": 1.41,
      "ma50": 241.13,
      "avgVol20": 506911,
      "high52w": 320.99,
      "high3m": 320.99,
      "vcpScore": 2,
      "vcpDepth": 15,
      "vcpBaseNumber": 6,
      "vcpPivot": 320.99,
      "vcpBaseDays": 5,
      "vcpPriorPullbackPct": 1.4,
      "qlibScore": 87,
      "qlibSubs": {
        "kmid": 74,
        "breakout": 89,
        "roc20": 99,
        "contract": 53,
        "volExp": 82,
        "chip": 99,
        "align": 99,
        "accel": 99
      },
      "isLeader": true,
      "isDiscovery": true,
      "earningsDate": 1785974400,
      "daysToEarnings": 37,
      "shortPctOfFloat": 0.101,
      "shortRatio": 8.48,
      "recentUpgrades": [],
      "recentDowngrades": [],
      "surpriseHistory": [
        {
          "qtr": "2025-06-30 00:00:00",
          "actual": 1.6,
          "estimate": 1.42143,
          "surprisePct": 0.12560001
        },
        {
          "qtr": "2025-09-30 00:00:00",
          "actual": 3.09,
          "estimate": 1.92571,
          "surprisePct": 0.6046
        },
        {
          "qtr": "2025-12-31 00:00:00",
          "actual": 2.02,
          "estimate": 1.49714,
          "surprisePct": 0.34919998
        },
        {
          "qtr": "2026-03-31 00:00:00",
          "actual": 1.63,
          "estimate": 1.80333,
          "surprisePct": -0.096099995
        }
      ],
      "recommendation": {
        "strongBuy": 2,
        "buy": 7,
        "hold": 0,
        "sell": 0,
        "strongSell": 0
      },
      "rsRating": 75,
      "compositeScore": 75,
      "discoScore": 58,
      "epsRevision": {
        "current": 9.1014,
        "pct90d": 5.51,
        "pct30d": 0.06,
        "pct7d": 0
      },
      "epsRevisionCounts": {
        "up7d": 1,
        "up30d": 2,
        "down7d": 1,
        "down30d": 2
      }
    },
    {
      "symbol": "XERS",
      "name": "Xeris Biopharma Holdings, Inc.",
      "price": 7.92,
      "changePct": 2.33,
      "ret1m": 30.48,
      "ret3m": 36.55,
      "ret6m": 6.59,
      "ret12_1": 30.26,
      "rs12_1": 7.45,
      "sector": "Healthcare",
      "industry": "Drug Manufacturers - Specialty & Generic",
      "sectorEtf": "XLV",
      "sectorRS": null,
      "accel": 2.5,
      "volExpand": 1.42,
      "volTrend": 1.07,
      "ma50": 6.47,
      "avgVol20": 2073190,
      "high52w": 10.08,
      "high3m": 7.97,
      "vcpScore": 3,
      "vcpDepth": 9,
      "vcpBaseNumber": 3,
      "vcpPivot": 7.97,
      "vcpBaseDays": 5,
      "vcpPriorPullbackPct": 0.3,
      "qlibScore": 77,
      "qlibSubs": {
        "kmid": 48,
        "breakout": 95,
        "roc20": 99,
        "contract": 58,
        "volExp": 26,
        "chip": 92,
        "align": 99,
        "accel": 99
      },
      "isLeader": true,
      "isDiscovery": true,
      "earningsDate": 1785974400,
      "daysToEarnings": 37,
      "shortPctOfFloat": 0.076799996,
      "shortRatio": 8.22,
      "recentUpgrades": [],
      "recentDowngrades": [],
      "surpriseHistory": [
        {
          "qtr": "2025-06-30 00:00:00",
          "actual": -0.01,
          "estimate": -0.03,
          "surprisePct": 0.6667
        },
        {
          "qtr": "2025-09-30 00:00:00",
          "actual": 0,
          "estimate": 0.00333,
          "surprisePct": -1
        },
        {
          "qtr": "2025-12-31 00:00:00",
          "actual": 0.06,
          "estimate": 0.045,
          "surprisePct": 0.33330002
        },
        {
          "qtr": "2026-03-31 00:00:00",
          "actual": 0.01,
          "estimate": -0.00067,
          "surprisePct": 15.925401
        }
      ],
      "recommendation": {
        "strongBuy": 1,
        "buy": 5,
        "hold": 1,
        "sell": 0,
        "strongSell": 0
      },
      "rsRating": 42,
      "compositeScore": 49,
      "discoScore": 58,
      "epsRevision": {
        "current": 0.1425,
        "pct90d": -54.69,
        "pct30d": 0.18,
        "pct7d": -10.75
      },
      "epsRevisionCounts": {
        "up7d": 1,
        "up30d": 2,
        "down7d": 1,
        "down30d": 1
      }
    },
    {
      "symbol": "AYI",
      "name": "Acuity Inc.",
      "price": 376.66,
      "changePct": 2.46,
      "ret1m": 22.69,
      "ret3m": 34.42,
      "ret6m": 2.05,
      "ret12_1": 0.15,
      "rs12_1": -22.66,
      "sector": "Industrials",
      "industry": "Electrical Equipment & Parts",
      "sectorEtf": "XLI",
      "sectorRS": null,
      "accel": 1.98,
      "volExpand": 1.62,
      "volTrend": 1.22,
      "ma50": 300.59,
      "avgVol20": 500367,
      "high52w": 380.17,
      "high3m": 378.65,
      "vcpScore": 0,
      "vcpDepth": null,
      "vcpBaseNumber": 0,
      "vcpPivot": null,
      "vcpBaseDays": 0,
      "vcpPriorPullbackPct": null,
      "qlibScore": 70,
      "qlibSubs": {
        "kmid": 46,
        "breakout": 96,
        "roc20": 78,
        "contract": 18,
        "volExp": 25,
        "chip": 99,
        "align": 99,
        "accel": 99
      },
      "isLeader": true,
      "isDiscovery": true,
      "earningsDate": 1782345600,
      "daysToEarnings": -5,
      "shortPctOfFloat": 0.0541,
      "shortRatio": 4.16,
      "recentUpgrades": [],
      "recentDowngrades": [],
      "surpriseHistory": [
        {
          "qtr": "2025-08-31 00:00:00",
          "actual": 5.2,
          "estimate": 4.83778,
          "surprisePct": 0.0749
        },
        {
          "qtr": "2025-11-30 00:00:00",
          "actual": 4.69,
          "estimate": 4.59125,
          "surprisePct": 0.0215
        },
        {
          "qtr": "2026-02-28 00:00:00",
          "actual": 4.14,
          "estimate": 3.99857,
          "surprisePct": 0.0354
        },
        {
          "qtr": "2026-05-31 00:00:00",
          "actual": 5.31,
          "estimate": 5.18576,
          "surprisePct": 0.024
        }
      ],
      "recommendation": {
        "strongBuy": 1,
        "buy": 3,
        "hold": 4,
        "sell": 0,
        "strongSell": 0
      },
      "rsRating": 1,
      "compositeScore": 27,
      "discoScore": 53,
      "epsRevision": {
        "current": 19.7136,
        "pct90d": -0.12,
        "pct30d": 1.01,
        "pct7d": 1.13
      },
      "epsRevisionCounts": {
        "up7d": 0,
        "up30d": 0,
        "down7d": 1,
        "down30d": 8
      }
    }
  ],
  "tripleResonance": [
    {
      "symbol": "KOD",
      "name": "Kodiak Sciences Inc",
      "price": 38.96,
      "rsRating": 99,
      "compositeScore": 84,
      "daysToEarnings": -54,
      "vcpScore": 4,
      "recentUpgradeCount": 0,
      "epsRevisionPct30d": 7.78,
      "epsRevisionNet7d": 4,
      "isDiscovery": false,
      "stars": 4,
      "reasons": [
        "VCP 4/6 (\u57fa\u5e95 1)",
        "RS 99",
        "EPS \u9810\u4f30\u4e0a\u4fee +7.8%/30d",
        "\u5206\u6790\u5e2b\u9810\u4f30\u6de8\u4e0a\u4fee +4/7d"
      ]
    },
    {
      "symbol": "STRL",
      "name": "Sterling Infrastructure, Inc.",
      "price": 839.36,
      "rsRating": 92,
      "compositeScore": 80,
      "daysToEarnings": 34,
      "vcpScore": 4,
      "recentUpgradeCount": 0,
      "epsRevisionPct30d": 5.09,
      "epsRevisionNet7d": 5,
      "isDiscovery": false,
      "stars": 4,
      "reasons": [
        "VCP 4/6 (\u57fa\u5e95 1)",
        "RS 92",
        "EPS \u9810\u4f30\u4e0a\u4fee +5.1%/30d",
        "\u5206\u6790\u5e2b\u9810\u4f30\u6de8\u4e0a\u4fee +5/7d"
      ]
    }
  ]
}